{"data": [{"games_played": 49, "player_id": 501, "season": 1997, "min": "25:46", "fgm": 3.06, "fga": 6.94, "fg3m": 0.08, "fg3a": 0.51, "ftm": 3.2, "fta": 3.67, "oreb": 0.71, "dreb": 2.55, "reb": 3.27, "ast": 4.84, "stl": 0.53, "blk": 0.16, "turnover": 1.98, "pf": 1.1, "pts": 9.41, "fg_pct": 0.441, "fg3_pct": 0.16, "ft_pct": 0.872}, {"games_played": 79, "player_id": 539, "season": 1997, "min": "29:26", "fgm": 5.38, "fga": 11.18, "fg3m": 0.34, "fg3a": 1.04, "ftm": 3.09, "fta": 4.51, "oreb": 1.87, "dreb": 3.16, "reb": 5.04, "ast": 2.11, "stl": 1.16, "blk": 1.1, "turnover": 1.77, "pf": 3.09, "pts": 14.19, "fg_pct": 0.481, "fg3_pct": 0.329, "ft_pct": 0.685}, {"games_played": 47, "player_id": 555, "season": 1997, "min": "21:06", "fgm": 4.34, "fga": 8.83, "fg3m": 0.45, "fg3a": 1.49, "ftm": 2.28, "fta": 3.09, "oreb": 1.6, "dreb": 3.11, "reb": 4.7, "ast": 1.28, "stl": 0.7, "blk": 0.34, "turnover": 1.53, "pf": 1.87, "pts": 11.4, "fg_pct": 0.492, "fg3_pct": 0.3, "ft_pct": 0.738}, {"games_played": 81, "player_id": 908, "season": 1997, "min": "38:07", "fgm": 4.35, "fga": 10.49, "fg3m": 0.9, "fg3a": 2.88, "ftm": 2.06, "fta": 2.58, "oreb": 1.32, "dreb": 4.95, "reb": 6.27, "ast": 9.07, "stl": 1.99, "blk": 0.31, "turnover": 3.21, "pf": 1.74, "pts": 11.65, "fg_pct": 0.414, "fg3_pct": 0.313, "ft_pct": 0.799}, {"games_played": 80, "player_id": 965, "season": 1997, "min": "29:51", "fgm": 6.03, "fga": 11.3, "fg3m": 0.0, "fg3a": 0.03, "ftm": 2.8, "fta": 3.98, "oreb": 2.54, "dreb": 4.98, "reb": 7.51, "ast": 1.29, "stl": 1.19, "blk": 1.66, "turnover": 1.75, "pf": 3.6, "pts": 14.85, "fg_pct": 0.533, "fg3_pct": 0.0, "ft_pct": 0.704}, {"games_played": 76, "player_id": 1039, "season": 1997, "min": "21:53", "fgm": 3.53, "fga": 7.68, "fg3m": 1.07, "fg3a": 2.57, "ftm": 0.97, "fta": 1.13, "oreb": 0.42, "dreb": 1.68, "reb": 2.11, "ast": 3.45, "stl": 0.83, "blk": 0.05, "turnover": 1.29, "pf": 1.91, "pts": 9.09, "fg_pct": 0.459, "fg3_pct": 0.415, "ft_pct": 0.86}, {"games_played": 8, "player_id": 1079, "season": 1997, "min": "4:19", "fgm": 0.88, "fga": 2.5, "fg3m": 0.13, "fg3a": 0.38, "ftm": 0.63, "fta": 0.75, "oreb": 0.5, "dreb": 1.13, "reb": 1.63, "ast": 0.13, "stl": 0.13, "blk": 0.25, "turnover": 0.75, "pf": 1.63, "pts": 2.5, "fg_pct": 0.35, "fg3_pct": 0.333, "ft_pct": 0.833}, {"games_played": 33, "player_id": 1135, "season": 1997, "min": "4:52", "fgm": 1.18, "fga": 1.94, "fg3m": 0.09, "fg3a": 0.18, "ftm": 0.33, "fta": 0.52, "oreb": 0.3, "dreb": 0.45, "reb": 0.76, "ast": 0.36, "stl": 0.3, "blk": 0.0, "turnover": 0.64, "pf": 0.52, "pts": 2.79, "fg_pct": 0.609, "fg3_pct": 0.5, "ft_pct": 0.647}, {"games_played": 70, "player_id": 2866, "season": 1997, "min": "18:51", "fgm": 1.36, "fga": 2.86, "fg3m": 0.0, "fg3a": 0.0, "ftm": 0.93, "fta": 1.33, "oreb": 1.5, "dreb": 2.89, "reb": 4.39, "ast": 0.69, "stl": 0.47, "blk": 0.83, "turnover": 0.41, "pf": 1.91, "pts": 3.64, "fg_pct": 0.475, "fg3_pct": 0, "ft_pct": 0.699}, {"games_played": 62, "player_id": 2883, "season": 1997, "min": "19:14", "fgm": 2.79, "fga": 6.84, "fg3m": 1.15, "fg3a": 3.35, "ftm": 0.58, "fta": 0.76, "oreb": 0.73, "dreb": 2.77, "reb": 3.5, "ast": 1.32, "stl": 0.87, "blk": 0.21, "turnover": 1.02, "pf": 2.1, "pts": 7.31, "fg_pct": 0.408, "fg3_pct": 0.341, "ft_pct": 0.766}, {"games_played": 67, "player_id": 2955, "season": 1997, "min": "33:08", "fgm": 5.94, "fga": 14.0, "fg3m": 1.73, "fg3a": 4.55, "ftm": 2.13, "fta": 2.75, "oreb": 0.42, "dreb": 2.13, "reb": 2.55, "ast": 2.97, "stl": 1.04, "blk": 0.21, "turnover": 1.69, "pf": 1.51, "pts": 15.75, "fg_pct": 0.424, "fg3_pct": 0.38, "ft_pct": 0.777}, {"games_played": 69, "player_id": 2965, "season": 1997, "min": "15:51", "fgm": 1.54, "fga": 3.2, "fg3m": 0.0, "fg3a": 0.01, "ftm": 1.06, "fta": 1.38, "oreb": 1.32, "dreb": 2.19, "reb": 3.51, "ast": 0.65, "stl": 0.51, "blk": 0.22, "turnover": 0.84, "pf": 2.55, "pts": 4.13, "fg_pct": 0.48, "fg3_pct": 0.0, "ft_pct": 0.768}, {"games_played": 70, "player_id": 3006, "season": 1997, "min": "25:40", "fgm": 5.57, "fga": 10.8, "fg3m": 0.0, "fg3a": 0.1, "ftm": 2.39, "fta": 3.23, "oreb": 1.57, "dreb": 4.03, "reb": 5.6, "ast": 1.99, "stl": 1.01, "blk": 0.66, "turnover": 1.43, "pf": 2.87, "pts": 13.53, "fg_pct": 0.516, "fg3_pct": 0.0, "ft_pct": 0.739}]}