{"data":[{"player_id":830,"team_id":18},{"player_id":929,"team_id":18},{"player_id":1478,"team_id":18},{"player_id":975,"team_id":18},{"player_id":950,"team_id":18},{"player_id":1251,"team_id":18},{"player_id":761,"team_id":18},{"player_id":994,"team_id":18},{"player_id":1113,"team_id":18},{"player_id":750,"team_id":18},{"player_id":1179,"team_id":18},{"player_id":971,"team_id":18},{"player_id":842,"team_id":18},{"player_id":1300,"team_id":18},{"player_id":1375,"team_id":18},{"player_id":1220,"team_id":18},{"player_id":1477,"team_id":18}]}
