{"data":[{"ast":2.69,"blk":0.98,"dreb":6.67,"fg3_pct":0.421,"fg3a":1.49,"fg3m":0.63,"fg_pct":0.481,"fga":18.47,"fgm":8.89,"ft_pct":0.915,"fta":7.23,"ftm":6.62,"games_played":81,"seconds":2250.0,"oreb":0.99,"pf":2.57,"player_id":346,"pts":25.02,"reb":7.65,"season":2009,"stl":0.86,"turnover":1.84},{"ast":9.05,"blk":0.44,"dreb":4.96,"fg3_pct":0.425,"fg3a":5.18,"fg3m":2.2,"fg_pct":0.423,"fga":8.39,"fgm":3.55,"ft_pct":0.808,"fta":1.24,"ftm":1.0,"games_played":80,"seconds":2160.0,"oreb":0.6,"pf":1.78,"player_id":908,"pts":10.3,"reb":5.56,"season":2009,"stl":1.81,"turnover":2.44},{"ast":3.79,"blk":0.22,"dreb":1.57,"fg3_pct":0.365,"fg3a":4.84,"fg3m":1.77,"fg_pct":0.438,"fga":13.52,"fgm":5.92,"ft_pct":0.866,"fta":3.48,"ftm":3.01,"games_played":77,"seconds":1978.0,"oreb":0.25,"pf":1.84,"player_id":1242,"pts":16.62,"reb":1.82,"season":2009,"stl":1.22,"turnover":1.42},{"ast":1.43,"blk":0.81,"dreb":4.25,"fg3_pct":0.158,"fg3a":0.25,"fg3m":0.04,"fg_pct":0.508,"fga":10.37,"fgm":5.27,"ft_pct":0.755,"fta":1.85,"ftm":1.4,"games_played":75,"seconds":1908.0,"oreb":2.11,"pf":1.88,"player_id":1226,"pts":11.97,"reb":6.36,"season":2009,"stl":0.92,"turnover":1.32},{"ast":1.37,"blk":0.31,"dreb":2.71,"fg3_pct":0.267,"fg3a":2.46,"fg3m":0.66,"fg_pct":0.405,"fga":11.09,"fgm":4.49,"ft_pct":0.784,"fta":3.97,"ftm":3.11,"games_played":35,"seconds":1573.0,"oreb":0.86,"pf":2.6,"player_id":1470,"pts":12.74,"reb":3.57,"season":2009,"stl":0.74,"turnover":1.31},{"ast":0.67,"blk":0.83,"dreb":4.79,"fg3_pct":0.125,"fg3a":0.11,"fg3m":0.01,"fg_pct":0.478,"fga":8.6,"fgm":4.11,"ft_pct":0.861,"fta":3.09,"ftm":2.66,"games_played":70,"seconds":1504.0,"oreb":2.96,"pf":2.77,"player_id":1441,"pts":10.9,"reb":7.74,"season":2009,"stl":0.59,"turnover":1.54},{"ast":0.56,"blk":1.4,"dreb":4.95,"fg3_pct":0.333,"fg3a":0.05,"fg3m":0.02,"fg_pct":0.624,"fga":3.87,"fgm":2.42,"ft_pct":0.604,"fta":1.84,"ftm":1.11,"games_played":55,"seconds":1396.0,"oreb":2.33,"pf":2.78,"player_id":1012,"pts":5.96,"reb":7.27,"season":2009,"stl":0.27,"turnover":1.11},{"ast":3.31,"blk":0.08,"dreb":1.65,"fg3_pct":0.357,"fg3a":2.01,"fg3m":0.72,"fg_pct":0.44,"fga":6.76,"fgm":2.97,"ft_pct":0.844,"fta":1.15,"ftm":0.97,"games_played":78,"seconds":1188.0,"oreb":0.22,"pf":1.53,"player_id":29,"pts":7.64,"reb":1.87,"season":2009,"stl":0.45,"turnover":1.31},{"ast":0.54,"blk":0.75,"dreb":2.95,"fg3_pct":0.189,"fg3a":0.65,"fg3m":0.12,"fg_pct":0.382,"fga":4.46,"fgm":1.7,"ft_pct":0.855,"fta":1.09,"ftm":0.93,"games_played":57,"seconds":1029.0,"oreb":1.89,"pf":1.98,"player_id":1611,"pts":4.46,"reb":4.84,"season":2009,"stl":0.49,"turnover":0.86},{"ast":0.78,"blk":0.11,"dreb":1.56,"fg3_pct":0.372,"fg3a":2.39,"fg3m":0.89,"fg_pct":0.462,"fga":5.89,"fgm":2.72,"ft_pct":0.875,"fta":1.33,"ftm":1.17,"games_played":18,"seconds":950.0,"oreb":0.72,"pf":1.72,"player_id":1116,"pts":7.5,"reb":2.28,"season":2009,"stl":0.56,"turnover":0.78},{"ast":0.63,"blk":0.3,"dreb":1.76,"fg3_pct":0.297,"fg3a":1.39,"fg3m":0.41,"fg_pct":0.425,"fga":3.17,"fgm":1.35,"ft_pct":0.583,"fta":0.52,"ftm":0.3,"games_played":46,"seconds":893.0,"oreb":0.74,"pf":2.04,"player_id":1288,"pts":3.41,"reb":2.5,"season":2009,"stl":0.57,"turnover":0.54},{"ast":1.32,"blk":0.21,"dreb":1.18,"fg3_pct":0.409,"fg3a":1.96,"fg3m":0.8,"fg_pct":0.518,"fga":5.34,"fgm":2.77,"ft_pct":0.808,"fta":0.93,"ftm":0.75,"games_played":56,"seconds":749.0,"oreb":0.21,"pf":1.5,"player_id":1838,"pts":7.09,"reb":1.39,"season":2009,"stl":0.52,"turnover":0.96}]}
