{"data":[{"ast":5.32,"blk":0.46,"dreb":4.2,"fg3_pct":0.286,"fg3a":2.8,"fg3m":0.8,"fg_pct":0.42,"fga":14.34,"fgm":6.02,"ft_pct":0.706,"fta":4.22,"ftm":2.98,"games_played":50,"seconds":2335.0,"oreb":1.48,"pf":2.22,"player_id":799,"pts":15.82,"reb":5.68,"season":1998,"stl":2.22,"turnover":3.0},{"ast":1.94,"blk":0.32,"dreb":4.81,"fg3_pct":0.347,"fg3a":5.89,"fg3m":2.04,"fg_pct":0.395,"fga":13.62,"fgm":5.38,"ft_pct":0.611,"fta":3.45,"ftm":2.11,"games_played":47,"seconds":2016.0,"oreb":1.09,"pf":1.53,"player_id":512,"pts":14.91,"reb":5.89,"season":1998,"stl":1.36,"turnover":1.77},{"ast":1.8,"blk":1.2,"dreb":4.68,"fg3_pct":0.0,"fg3a":0.04,"fg3m":0.0,"fg_pct":0.434,"fga":9.12,"fgm":3.96,"ft_pct":0.671,"fta":1.4,"ftm":0.94,"games_played":50,"seconds":1986.0,"oreb":2.34,"pf":1.98,"player_id":2929,"pts":8.86,"reb":7.02,"season":1998,"stl":0.92,"turnover":0.88},{"ast":6.7,"blk":0.08,"dreb":2.54,"fg3_pct":0.365,"fg3a":3.78,"fg3m":1.38,"fg_pct":0.441,"fga":10.44,"fgm":4.6,"ft_pct":0.904,"fta":3.56,"ftm":3.22,"games_played":50,"seconds":1804.0,"oreb":1.06,"pf":1.8,"player_id":933,"pts":13.8,"reb":3.6,"season":1998,"stl":2.16,"turnover":3.16},{"ast":1.81,"blk":1.39,"dreb":3.65,"fg3_pct":0.0,"fg3a":0.1,"fg3m":0.0,"fg_pct":0.545,"fga":4.97,"fgm":2.71,"ft_pct":0.432,"fta":2.61,"ftm":1.13,"games_played":31,"seconds":1645.0,"oreb":1.74,"pf":2.55,"player_id":866,"pts":6.55,"reb":5.39,"season":1998,"stl":1.29,"turnover":1.87},{"ast":1.82,"blk":0.71,"dreb":3.14,"fg3_pct":0.286,"fg3a":0.14,"fg3m":0.04,"fg_pct":0.408,"fga":9.24,"fgm":3.78,"ft_pct":0.669,"fta":3.2,"ftm":2.14,"games_played":49,"seconds":1539.0,"oreb":1.69,"pf":2.55,"player_id":1031,"pts":9.73,"reb":4.84,"season":1998,"stl":0.96,"turnover":2.33},{"ast":0.9,"blk":0.12,"dreb":2.52,"fg3_pct":0.4,"fg3a":0.5,"fg3m":0.2,"fg_pct":0.462,"fga":6.4,"fgm":2.96,"ft_pct":0.713,"fta":2.86,"ftm":2.04,"games_played":50,"seconds":1338.0,"oreb":1.76,"pf":2.24,"player_id":1159,"pts":8.16,"reb":4.28,"season":1998,"stl":0.6,"turnover":1.46},{"ast":0.39,"blk":0.16,"dreb":2.16,"fg3_pct":0.0,"fg3a":0.05,"fg3m":0.0,"fg_pct":0.422,"fga":4.09,"fgm":1.73,"ft_pct":0.717,"fta":2.25,"ftm":1.61,"games_played":44,"seconds":954.0,"oreb":1.5,"pf":1.45,"player_id":723,"pts":5.07,"reb":3.66,"season":1998,"stl":0.34,"turnover":0.84},{"ast":0.41,"blk":0.35,"dreb":1.67,"fg3_pct":0.0,"fg3a":0.0,"fg3m":0.0,"fg_pct":0.468,"fga":5.45,"fgm":2.55,"ft_pct":0.675,"fta":1.63,"ftm":1.1,"games_played":49,"seconds":954.0,"oreb":1.35,"pf":2.39,"player_id":1158,"pts":6.2,"reb":3.02,"season":1998,"stl":0.39,"turnover":0.53},{"ast":1.91,"blk":0.0,"dreb":1.16,"fg3_pct":0.467,"fg3a":0.47,"fg3m":0.22,"fg_pct":0.455,"fga":2.75,"fgm":1.25,"ft_pct":0.857,"fta":0.66,"ftm":0.56,"games_played":32,"seconds":667.0,"oreb":0.06,"pf":0.97,"player_id":2924,"pts":3.28,"reb":1.22,"season":1998,"stl":0.38,"turnover":0.78},{"ast":0.33,"blk":0.0,"dreb":0.33,"fg3_pct":0.0,"fg3a":0.0,"fg3m":0.0,"fg_pct":0.0,"fga":3.0,"fgm":0.0,"ft_pct":1.0,"fta":0.67,"ftm":0.67,"games_played":3,"seconds":572.0,"oreb":0.0,"pf":1.0,"player_id":2959,"pts":0.67,"reb":0.33,"season":1998,"stl":0.0,"turnover":1.0},{"ast":0.59,"blk":0.04,"dreb":1.52,"fg3_pct":0.263,"fg3a":0.7,"fg3m":0.19,"fg_pct":0.379,"fga":4.89,"fgm":1.85,"ft_pct":0.69,"fta":1.56,"ftm":1.07,"games_played":27,"seconds":556.0,"oreb":1.11,"pf":0.7,"player_id":530,"pts":4.96,"reb":2.63,"season":1998,"stl":0.15,"turnover":0.85}]}
