{"data": [{"games_played": 59, "player_id": 77, "season": 2011, "min": "15:54", "fgm": 2.59, "fga": 6.05, "fg3m": 0.25, "fg3a": 0.76, "ftm": 1.76, "fta": 2.42, "oreb": 0.97, "dreb": 1.27, "reb": 2.24, "ast": 0.93, "stl": 0.46, "blk": 0.08, "turnover": 0.86, "pf": 1.42, "pts": 7.2, "fg_pct": 0.429, "fg3_pct": 0.333, "ft_pct": 0.727}, {"games_played": 24, "player_id": 84, "season": 2011, "min": "14:30", "fgm": 1.79, "fga": 4.38, "fg3m": 0.29, "fg3a": 0.79, "ftm": 0.58, "fta": 0.67, "oreb": 1.17, "dreb": 1.04, "reb": 2.21, "ast": 0.75, "stl": 0.5, "blk": 0.04, "turnover": 0.46, "pf": 1.54, "pts": 4.46, "fg_pct": 0.41, "fg3_pct": 0.368, "ft_pct": 0.875}, {"games_played": 65, "player_id": 153, "season": 2011, "min": "21:09", "fgm": 3.42, "fga": 6.85, "fg3m": 0.0, "fg3a": 0.0, "ftm": 1.94, "fta": 2.98, "oreb": 2.43, "dreb": 4.11, "reb": 6.54, "ast": 0.66, "stl": 0.58, "blk": 1.0, "turnover": 1.58, "pf": 2.23, "pts": 8.77, "fg_pct": 0.499, "fg3_pct": 0, "ft_pct": 0.649}, {"games_played": 63, "player_id": 195, "season": 2011, "min": "27:38", "fgm": 3.83, "fga": 8.6, "fg3m": 1.22, "fg3a": 3.38, "ftm": 2.48, "fta": 3.32, "oreb": 0.19, "dreb": 1.59, "reb": 1.78, "ast": 5.02, "stl": 1.02, "blk": 0.21, "turnover": 1.94, "pf": 2.16, "pts": 11.35, "fg_pct": 0.445, "fg3_pct": 0.362, "ft_pct": 0.746}, {"games_played": 66, "player_id": 204, "season": 2011, "min": "30:31", "fgm": 4.05, "fga": 8.88, "fg3m": 0.83, "fg3a": 2.41, "ftm": 2.92, "fta": 3.52, "oreb": 0.89, "dreb": 2.59, "reb": 3.48, "ast": 3.14, "stl": 0.8, "blk": 0.62, "turnover": 1.65, "pf": 1.61, "pts": 11.85, "fg_pct": 0.456, "fg3_pct": 0.346, "ft_pct": 0.832}, {"games_played": 66, "player_id": 253, "season": 2011, "min": "13:14", "fgm": 1.77, "fga": 3.58, "fg3m": 0.0, "fg3a": 0.02, "ftm": 1.06, "fta": 1.59, "oreb": 1.62, "dreb": 2.59, "reb": 4.21, "ast": 0.12, "stl": 0.27, "blk": 0.35, "turnover": 0.82, "pf": 1.32, "pts": 4.61, "fg_pct": 0.496, "fg3_pct": 0.0, "ft_pct": 0.667}, {"games_played": 56, "player_id": 316, "season": 2011, "min": "20:26", "fgm": 3.16, "fga": 8.3, "fg3m": 0.82, "fg3a": 2.68, "ftm": 1.93, "fta": 2.43, "oreb": 0.48, "dreb": 1.59, "reb": 2.07, "ast": 1.23, "stl": 0.82, "blk": 0.32, "turnover": 0.95, "pf": 2.18, "pts": 9.07, "fg_pct": 0.381, "fg3_pct": 0.307, "ft_pct": 0.794}, {"games_played": 64, "player_id": 318, "season": 2011, "min": "32:48", "fgm": 6.66, "fga": 13.45, "fg3m": 0.11, "fg3a": 0.48, "ftm": 3.16, "fta": 3.98, "oreb": 2.81, "dreb": 5.98, "reb": 8.8, "ast": 2.34, "stl": 1.84, "blk": 0.81, "turnover": 1.75, "pf": 3.47, "pts": 16.58, "fg_pct": 0.495, "fg3_pct": 0.226, "ft_pct": 0.792}, {"games_played": 34, "player_id": 1339, "season": 2011, "min": "23:25", "fgm": 2.38, "fga": 5.12, "fg3m": 1.0, "fg3a": 2.56, "ftm": 0.62, "fta": 0.74, "oreb": 0.18, "dreb": 1.26, "reb": 1.44, "ast": 1.12, "stl": 0.38, "blk": 0.06, "turnover": 0.62, "pf": 2.29, "pts": 6.38, "fg_pct": 0.466, "fg3_pct": 0.391, "ft_pct": 0.84}, {"games_played": 50, "player_id": 1342, "season": 2011, "min": "20:39", "fgm": 1.08, "fga": 3.2, "fg3m": 0.2, "fg3a": 1.04, "ftm": 0.62, "fta": 0.92, "oreb": 0.6, "dreb": 1.82, "reb": 2.42, "ast": 4.34, "stl": 1.08, "blk": 0.44, "turnover": 1.7, "pf": 2.1, "pts": 2.98, "fg_pct": 0.338, "fg3_pct": 0.192, "ft_pct": 0.674}, {"games_played": 37, "player_id": 1344, "season": 2011, "min": "13:42", "fgm": 1.54, "fga": 3.81, "fg3m": 0.27, "fg3a": 1.0, "ftm": 0.35, "fta": 0.46, "oreb": 0.16, "dreb": 1.05, "reb": 1.22, "ast": 3.32, "stl": 0.46, "blk": 0.22, "turnover": 1.41, "pf": 1.27, "pts": 3.7, "fg_pct": 0.404, "fg3_pct": 0.27, "ft_pct": 0.765}, {"games_played": 43, "player_id": 1470, "season": 2011, "min": "23:02", "fgm": 3.35, "fga": 8.4, "fg3m": 0.21, "fg3a": 0.86, "ftm": 1.74, "fta": 2.26, "oreb": 0.91, "dreb": 2.77, "reb": 3.67, "ast": 1.16, "stl": 0.74, "blk": 0.23, "turnover": 1.23, "pf": 2.12, "pts": 8.65, "fg_pct": 0.399, "fg3_pct": 0.243, "ft_pct": 0.773}, {"games_played": 61, "player_id": 1553, "season": 2011, "min": "34:00", "fgm": 8.46, "fga": 17.18, "fg3m": 0.02, "fg3a": 0.07, "ftm": 2.25, "fta": 2.9, "oreb": 2.18, "dreb": 7.41, "reb": 9.59, "ast": 2.2, "stl": 0.77, "blk": 1.66, "turnover": 1.02, "pf": 2.54, "pts": 19.18, "fg_pct": 0.492, "fg3_pct": 0.25, "ft_pct": 0.774}, {"games_played": 4, "player_id": 1794, "season": 2011, "min": "7:35", "fgm": 1.0, "fga": 3.5, "fg3m": 0.5, "fg3a": 2.25, "ftm": 0.0, "fta": 0.0, "oreb": 0.0, "dreb": 0.5, "reb": 0.5, "ast": 0.25, "stl": 0.0, "blk": 0.0, "turnover": 1.25, "pf": 1.0, "pts": 2.5, "fg_pct": 0.286, "fg3_pct": 0.222, "ft_pct": 0}, {"games_played": 29, "player_id": 1890, "season": 2011, "min": "7:28", "fgm": 0.93, "fga": 1.45, "fg3m": 0.0, "fg3a": 0.03, "ftm": 0.28, "fta": 0.55, "oreb": 0.66, "dreb": 1.07, "reb": 1.72, "ast": 0.45, "stl": 0.21, "blk": 0.83, "turnover": 0.17, "pf": 0.79, "pts": 2.14, "fg_pct": 0.643, "fg3_pct": 0.0, "ft_pct": 0.5}]}