{"data": [{"games_played": 43, "player_id": 88, "season": 2002, "min": "34:11", "fgm": 8.26, "fga": 17.67, "fg3m": 1.05, "fg3a": 3.05, "ftm": 3.0, "fta": 3.72, "oreb": 1.37, "dreb": 3.0, "reb": 4.37, "ast": 3.33, "stl": 1.12, "blk": 0.95, "turnover": 1.72, "pf": 2.81, "pts": 20.56, "fg_pct": 0.467, "fg3_pct": 0.344, "ft_pct": 0.806}, {"games_played": 29, "player_id": 509, "season": 2002, "min": "18:35", "fgm": 1.62, "fga": 4.21, "fg3m": 0.03, "fg3a": 0.14, "ftm": 0.9, "fta": 1.1, "oreb": 1.03, "dreb": 2.48, "reb": 3.52, "ast": 0.45, "stl": 0.03, "blk": 0.31, "turnover": 1.03, "pf": 2.83, "pts": 4.17, "fg_pct": 0.385, "fg3_pct": 0.25, "ft_pct": 0.812}, {"games_played": 53, "player_id": 833, "season": 2002, "min": "35:48", "fgm": 4.92, "fga": 12.09, "fg3m": 0.0, "fg3a": 0.0, "ftm": 4.08, "fta": 5.28, "oreb": 2.45, "dreb": 5.79, "reb": 8.25, "ast": 2.47, "stl": 0.43, "blk": 1.17, "turnover": 2.23, "pf": 2.83, "pts": 13.92, "fg_pct": 0.407, "fg3_pct": 0, "ft_pct": 0.771}, {"games_played": 29, "player_id": 835, "season": 2002, "min": "23:11", "fgm": 3.66, "fga": 10.41, "fg3m": 1.17, "fg3a": 3.69, "ftm": 1.17, "fta": 1.62, "oreb": 0.52, "dreb": 1.52, "reb": 2.03, "ast": 2.45, "stl": 1.21, "blk": 0.17, "turnover": 1.97, "pf": 1.72, "pts": 9.66, "fg_pct": 0.351, "fg3_pct": 0.318, "ft_pct": 0.723}, {"games_played": 63, "player_id": 993, "season": 2002, "min": "30:36", "fgm": 5.16, "fga": 12.84, "fg3m": 1.46, "fg3a": 4.0, "ftm": 2.48, "fta": 3.08, "oreb": 0.76, "dreb": 2.6, "reb": 3.37, "ast": 2.29, "stl": 0.94, "blk": 0.33, "turnover": 1.63, "pf": 2.48, "pts": 14.25, "fg_pct": 0.402, "fg3_pct": 0.365, "ft_pct": 0.804}, {"games_played": 71, "player_id": 1013, "season": 2002, "min": "32:59", "fgm": 3.76, "fga": 7.54, "fg3m": 0.01, "fg3a": 0.08, "ftm": 2.2, "fta": 3.96, "oreb": 3.25, "dreb": 5.9, "reb": 9.15, "ast": 1.34, "stl": 1.63, "blk": 0.37, "turnover": 1.38, "pf": 2.77, "pts": 9.73, "fg_pct": 0.499, "fg3_pct": 0.167, "ft_pct": 0.555}, {"games_played": 78, "player_id": 1100, "season": 2002, "min": "33:52", "fgm": 5.08, "fga": 11.6, "fg3m": 0.62, "fg3a": 1.87, "ftm": 2.4, "fta": 3.06, "oreb": 0.71, "dreb": 2.44, "reb": 3.14, "ast": 5.33, "stl": 1.42, "blk": 0.27, "turnover": 1.64, "pf": 2.18, "pts": 13.17, "fg_pct": 0.438, "fg3_pct": 0.329, "ft_pct": 0.782}, {"games_played": 67, "player_id": 1150, "season": 2002, "min": "20:24", "fgm": 2.9, "fga": 5.9, "fg3m": 0.0, "fg3a": 0.0, "ftm": 1.03, "fta": 1.88, "oreb": 1.42, "dreb": 3.88, "reb": 5.3, "ast": 0.64, "stl": 0.42, "blk": 0.9, "turnover": 1.43, "pf": 2.42, "pts": 6.82, "fg_pct": 0.491, "fg3_pct": 0, "ft_pct": 0.548}, {"games_played": 47, "player_id": 1269, "season": 2002, "min": "20:54", "fgm": 2.96, "fga": 7.13, "fg3m": 1.09, "fg3a": 2.77, "ftm": 0.79, "fta": 1.15, "oreb": 0.45, "dreb": 1.83, "reb": 2.28, "ast": 4.09, "stl": 0.81, "blk": 0.32, "turnover": 1.83, "pf": 2.55, "pts": 7.79, "fg_pct": 0.415, "fg3_pct": 0.392, "ft_pct": 0.685}, {"games_played": 16, "player_id": 1273, "season": 2002, "min": "6:30", "fgm": 0.94, "fga": 1.56, "fg3m": 0.0, "fg3a": 0.0, "ftm": 0.63, "fta": 0.75, "oreb": 0.25, "dreb": 1.19, "reb": 1.44, "ast": 0.0, "stl": 0.25, "blk": 0.69, "turnover": 0.38, "pf": 1.0, "pts": 2.5, "fg_pct": 0.6, "fg3_pct": 0, "ft_pct": 0.833}, {"games_played": 82, "player_id": 1303, "season": 2002, "min": "35:54", "fgm": 5.13, "fga": 13.09, "fg3m": 1.41, "fg3a": 4.2, "ftm": 2.38, "fta": 3.01, "oreb": 1.18, "dreb": 3.24, "reb": 4.43, "ast": 2.29, "stl": 1.07, "blk": 0.39, "turnover": 1.56, "pf": 2.83, "pts": 14.06, "fg_pct": 0.392, "fg3_pct": 0.337, "ft_pct": 0.789}, {"games_played": 3, "player_id": 1320, "season": 2002, "min": "3:42", "fgm": 0.67, "fga": 1.67, "fg3m": 0.0, "fg3a": 0.0, "ftm": 0.67, "fta": 0.67, "oreb": 0.33, "dreb": 1.0, "reb": 1.33, "ast": 0.0, "stl": 0.33, "blk": 0.0, "turnover": 0.33, "pf": 0.67, "pts": 2.0, "fg_pct": 0.4, "fg3_pct": 0, "ft_pct": 1.0}, {"games_played": 22, "player_id": 1330, "season": 2002, "min": "16:38", "fgm": 1.95, "fga": 4.36, "fg3m": 0.0, "fg3a": 0.0, "ftm": 1.55, "fta": 2.14, "oreb": 1.32, "dreb": 2.41, "reb": 3.73, "ast": 0.32, "stl": 0.36, "blk": 1.45, "turnover": 0.95, "pf": 2.64, "pts": 5.45, "fg_pct": 0.448, "fg3_pct": 0, "ft_pct": 0.723}, {"games_played": 67, "player_id": 1350, "season": 2002, "min": "19:34", "fgm": 2.25, "fga": 4.69, "fg3m": 0.01, "fg3a": 0.09, "ftm": 0.52, "fta": 1.0, "oreb": 2.42, "dreb": 3.69, "reb": 6.1, "ast": 1.0, "stl": 0.24, "blk": 0.48, "turnover": 1.13, "pf": 1.87, "pts": 5.04, "fg_pct": 0.481, "fg3_pct": 0.167, "ft_pct": 0.522}, {"games_played": 5, "player_id": 1356, "season": 2002, "min": "23:02", "fgm": 2.2, "fga": 7.0, "fg3m": 0.0, "fg3a": 0.4, "ftm": 1.2, "fta": 1.6, "oreb": 0.6, "dreb": 2.4, "reb": 3.0, "ast": 0.6, "stl": 0.2, "blk": 0.0, "turnover": 1.2, "pf": 2.8, "pts": 5.6, "fg_pct": 0.314, "fg3_pct": 0.0, "ft_pct": 0.75}, {"games_played": 7, "player_id": 1420, "season": 2002, "min": "11:09", "fgm": 1.29, "fga": 3.57, "fg3m": 0.0, "fg3a": 0.0, "ftm": 0.71, "fta": 1.14, "oreb": 1.29, "dreb": 2.0, "reb": 3.29, "ast": 0.71, "stl": 0.14, "blk": 0.43, "turnover": 0.43, "pf": 1.86, "pts": 3.29, "fg_pct": 0.36, "fg3_pct": 0, "ft_pct": 0.625}, {"games_played": 51, "player_id": 1421, "season": 2002, "min": "13:04", "fgm": 1.47, "fga": 3.8, "fg3m": 0.35, "fg3a": 1.06, "ftm": 0.57, "fta": 0.84, "oreb": 0.31, "dreb": 0.84, "reb": 1.16, "ast": 0.43, "stl": 0.37, "blk": 0.31, "turnover": 0.88, "pf": 1.1, "pts": 3.86, "fg_pct": 0.387, "fg3_pct": 0.333, "ft_pct": 0.674}]}