{"data": [{"games_played": 33, "player_id": 29, "season": 2006, "min": "5:47", "fgm": 0.85, "fga": 2.36, "fg3m": 0.18, "fg3a": 0.64, "ftm": 0.48, "fta": 0.73, "oreb": 0.21, "dreb": 0.55, "reb": 0.76, "ast": 0.73, "stl": 0.03, "blk": 0.03, "turnover": 0.42, "pf": 0.58, "pts": 2.36, "fg_pct": 0.359, "fg3_pct": 0.286, "ft_pct": 0.667}, {"games_played": 80, "player_id": 195, "season": 2006, "min": "26:01", "fgm": 3.65, "fga": 7.41, "fg3m": 0.18, "fg3a": 0.63, "ftm": 2.69, "fta": 3.26, "oreb": 0.56, "dreb": 1.89, "reb": 2.45, "ast": 3.7, "stl": 1.2, "blk": 0.26, "turnover": 1.83, "pf": 3.03, "pts": 10.16, "fg_pct": 0.492, "fg3_pct": 0.28, "ft_pct": 0.824}, {"games_played": 78, "player_id": 346, "season": 2006, "min": "36:09", "fgm": 8.63, "fga": 17.19, "fg3m": 0.92, "fg3a": 2.22, "ftm": 6.38, "fta": 7.06, "oreb": 1.56, "dreb": 7.32, "reb": 8.88, "ast": 3.37, "stl": 0.67, "blk": 0.79, "turnover": 2.14, "pf": 2.19, "pts": 24.56, "fg_pct": 0.502, "fg3_pct": 0.416, "ft_pct": 0.904}, {"games_played": 5, "player_id": 579, "season": 2006, "min": "8:31", "fgm": 1.0, "fga": 2.6, "fg3m": 0.0, "fg3a": 0.0, "ftm": 0.4, "fta": 0.4, "oreb": 0.4, "dreb": 1.2, "reb": 1.6, "ast": 0.2, "stl": 0.4, "blk": 0.2, "turnover": 0.4, "pf": 2.2, "pts": 2.4, "fg_pct": 0.385, "fg3_pct": 0, "ft_pct": 1.0}, {"games_played": 67, "player_id": 946, "season": 2006, "min": "24:05", "fgm": 4.18, "fga": 9.76, "fg3m": 0.93, "fg3a": 2.42, "ftm": 2.72, "fta": 3.21, "oreb": 0.58, "dreb": 1.58, "reb": 2.16, "ast": 2.79, "stl": 0.76, "blk": 0.15, "turnover": 1.75, "pf": 1.16, "pts": 12.0, "fg_pct": 0.428, "fg3_pct": 0.383, "ft_pct": 0.847}, {"games_played": 76, "player_id": 1012, "season": 2006, "min": "25:12", "fgm": 2.75, "fga": 4.39, "fg3m": 0.0, "fg3a": 0.0, "ftm": 1.57, "fta": 2.51, "oreb": 2.86, "dreb": 4.59, "reb": 7.45, "ast": 0.58, "stl": 0.32, "blk": 1.08, "turnover": 1.41, "pf": 3.14, "pts": 7.07, "fg_pct": 0.626, "fg3_pct": 0, "ft_pct": 0.623}, {"games_played": 67, "player_id": 1121, "season": 2006, "min": "19:24", "fgm": 2.12, "fga": 5.12, "fg3m": 0.37, "fg3a": 1.09, "ftm": 0.69, "fta": 0.91, "oreb": 0.33, "dreb": 1.18, "reb": 1.51, "ast": 3.0, "stl": 0.49, "blk": 0.04, "turnover": 1.13, "pf": 1.78, "pts": 5.3, "fg_pct": 0.414, "fg3_pct": 0.342, "ft_pct": 0.754}, {"games_played": 61, "player_id": 1132, "season": 2006, "min": "11:55", "fgm": 1.28, "fga": 3.64, "fg3m": 0.43, "fg3a": 1.49, "ftm": 0.74, "fta": 0.85, "oreb": 0.54, "dreb": 2.51, "reb": 3.05, "ast": 0.72, "stl": 0.23, "blk": 0.1, "turnover": 0.54, "pf": 1.11, "pts": 3.72, "fg_pct": 0.351, "fg3_pct": 0.286, "ft_pct": 0.865}, {"games_played": 60, "player_id": 1219, "season": 2006, "min": "21:23", "fgm": 2.43, "fga": 6.17, "fg3m": 0.88, "fg3a": 2.5, "ftm": 0.6, "fta": 0.8, "oreb": 0.95, "dreb": 2.6, "reb": 3.55, "ast": 0.55, "stl": 0.77, "blk": 0.38, "turnover": 0.85, "pf": 2.38, "pts": 6.35, "fg_pct": 0.395, "fg3_pct": 0.353, "ft_pct": 0.75}, {"games_played": 80, "player_id": 1242, "season": 2006, "min": "35:09", "fgm": 6.3, "fga": 13.04, "fg3m": 2.0, "fg3a": 4.58, "ftm": 1.96, "fta": 2.44, "oreb": 0.51, "dreb": 2.35, "reb": 2.86, "ast": 5.2, "stl": 1.01, "blk": 0.21, "turnover": 1.9, "pf": 2.11, "pts": 16.56, "fg_pct": 0.483, "fg3_pct": 0.437, "ft_pct": 0.805}, {"games_played": 76, "player_id": 1267, "season": 2006, "min": "18:02", "fgm": 1.62, "fga": 3.93, "fg3m": 0.42, "fg3a": 1.36, "ftm": 0.36, "fta": 0.45, "oreb": 0.46, "dreb": 1.62, "reb": 2.08, "ast": 0.92, "stl": 0.62, "blk": 0.09, "turnover": 0.53, "pf": 2.0, "pts": 4.01, "fg_pct": 0.411, "fg3_pct": 0.311, "ft_pct": 0.794}, {"games_played": 81, "player_id": 1367, "season": 2006, "min": "18:16", "fgm": 0.88, "fga": 1.86, "fg3m": 0.0, "fg3a": 0.01, "ftm": 0.59, "fta": 1.06, "oreb": 2.05, "dreb": 3.36, "reb": 5.41, "ast": 0.37, "stl": 0.49, "blk": 1.4, "turnover": 0.78, "pf": 3.01, "pts": 2.35, "fg_pct": 0.47, "fg3_pct": 0.0, "ft_pct": 0.558}, {"games_played": 70, "player_id": 1470, "season": 2006, "min": "35:04", "fgm": 7.04, "fga": 15.36, "fg3m": 1.31, "fg3a": 3.41, "ftm": 3.47, "fta": 4.2, "oreb": 1.86, "dreb": 4.93, "reb": 6.79, "ast": 1.81, "stl": 1.17, "blk": 0.8, "turnover": 1.76, "pf": 2.57, "pts": 18.87, "fg_pct": 0.459, "fg3_pct": 0.385, "ft_pct": 0.827}, {"games_played": 21, "player_id": 1532, "season": 2006, "min": "3:44", "fgm": 0.24, "fga": 0.76, "fg3m": 0.0, "fg3a": 0.0, "ftm": 0.33, "fta": 0.38, "oreb": 0.14, "dreb": 0.38, "reb": 0.52, "ast": 0.29, "stl": 0.14, "blk": 0.24, "turnover": 0.24, "pf": 0.81, "pts": 0.81, "fg_pct": 0.312, "fg3_pct": 0, "ft_pct": 0.875}, {"games_played": 32, "player_id": 1705, "season": 2006, "min": "6:41", "fgm": 0.69, "fga": 2.19, "fg3m": 0.16, "fg3a": 0.47, "ftm": 0.63, "fta": 1.03, "oreb": 0.03, "dreb": 0.63, "reb": 0.66, "ast": 0.22, "stl": 0.13, "blk": 0.09, "turnover": 0.47, "pf": 0.84, "pts": 2.16, "fg_pct": 0.314, "fg3_pct": 0.333, "ft_pct": 0.606}, {"games_played": 12, "player_id": 1706, "season": 2006, "min": "5:56", "fgm": 0.92, "fga": 1.42, "fg3m": 0.0, "fg3a": 0.0, "ftm": 0.58, "fta": 1.5, "oreb": 0.75, "dreb": 1.0, "reb": 1.75, "ast": 0.0, "stl": 0.08, "blk": 0.0, "turnover": 0.75, "pf": 0.67, "pts": 2.42, "fg_pct": 0.647, "fg3_pct": 0, "ft_pct": 0.389}]}