{"data":[{"ast":6.58,"blk":0.38,"dreb":3.34,"fg3_pct":0.345,"fg3a":4.03,"fg3m":1.39,"fg_pct":0.445,"fga":14.51,"fgm":6.45,"ft_pct":0.786,"fta":4.74,"ftm":3.73,"games_played":77,"seconds":2162.0,"oreb":1.97,"pf":3.0,"player_id":1232,"pts":18.03,"reb":5.31,"season":1999,"stl":1.53,"turnover":3.97},{"ast":2.91,"blk":0.39,"dreb":3.57,"fg3_pct":0.351,"fg3a":2.74,"fg3m":0.96,"fg_pct":0.473,"fga":9.49,"fgm":4.49,"ft_pct":0.767,"fta":3.09,"ftm":2.37,"games_played":82,"seconds":1978.0,"oreb":1.11,"pf":2.23,"player_id":1048,"pts":12.3,"reb":4.68,"season":1999,"stl":1.17,"turnover":2.37},{"ast":3.15,"blk":0.2,"dreb":6.9,"fg3_pct":0.231,"fg3a":1.3,"fg3m":0.3,"fg_pct":0.477,"fga":11.1,"fgm":5.3,"ft_pct":0.645,"fta":5.5,"ftm":3.55,"games_played":20,"seconds":1859.0,"oreb":3.55,"pf":2.4,"player_id":2937,"pts":14.45,"reb":10.45,"season":1999,"stl":0.7,"turnover":2.2},{"ast":2.57,"blk":0.4,"dreb":2.83,"fg3_pct":0.356,"fg3a":3.6,"fg3m":1.28,"fg_pct":0.43,"fga":12.54,"fgm":5.4,"ft_pct":0.847,"fta":4.36,"ftm":3.69,"games_played":81,"seconds":1849.0,"oreb":0.73,"pf":2.11,"player_id":1184,"pts":15.77,"reb":3.56,"season":1999,"stl":1.07,"turnover":2.3},{"ast":1.57,"blk":0.31,"dreb":4.03,"fg3_pct":0.262,"fg3a":1.69,"fg3m":0.44,"fg_pct":0.399,"fga":7.38,"fgm":2.94,"ft_pct":0.66,"fta":2.9,"ftm":1.92,"games_played":72,"seconds":1495.0,"oreb":2.04,"pf":2.32,"player_id":1233,"pts":8.25,"reb":6.07,"season":1999,"stl":0.75,"turnover":1.56},{"ast":2.07,"blk":0.58,"dreb":3.12,"fg3_pct":0.391,"fg3a":3.43,"fg3m":1.34,"fg_pct":0.458,"fga":8.96,"fgm":4.11,"ft_pct":0.821,"fta":1.62,"ftm":1.33,"games_played":76,"seconds":1467.0,"oreb":0.91,"pf":2.49,"player_id":732,"pts":10.88,"reb":4.03,"season":1999,"stl":0.64,"turnover":1.49},{"ast":0.4,"blk":1.91,"dreb":4.42,"fg3_pct":0.0,"fg3a":0.06,"fg3m":0.0,"fg_pct":0.537,"fga":6.18,"fgm":3.32,"ft_pct":0.649,"fta":3.2,"ftm":2.08,"games_played":65,"seconds":1459.0,"oreb":1.57,"pf":2.69,"player_id":1099,"pts":8.72,"reb":5.98,"season":1999,"stl":0.51,"turnover":1.09},{"ast":1.39,"blk":1.59,"dreb":4.75,"fg3_pct":0.0,"fg3a":0.05,"fg3m":0.0,"fg_pct":0.458,"fga":9.57,"fgm":4.39,"ft_pct":0.616,"fta":2.55,"ftm":1.57,"games_played":44,"seconds":1426.0,"oreb":1.48,"pf":2.0,"player_id":540,"pts":10.34,"reb":6.23,"season":1999,"stl":0.93,"turnover":1.66},{"ast":0.79,"blk":0.64,"dreb":3.34,"fg3_pct":0.071,"fg3a":0.26,"fg3m":0.02,"fg_pct":0.525,"fga":6.11,"fgm":3.21,"ft_pct":0.591,"fta":2.58,"ftm":1.53,"games_played":53,"seconds":1246.0,"oreb":1.85,"pf":1.45,"player_id":911,"pts":7.96,"reb":5.19,"season":1999,"stl":0.26,"turnover":1.19},{"ast":1.11,"blk":0.24,"dreb":2.24,"fg3_pct":0.439,"fg3a":3.15,"fg3m":1.38,"fg_pct":0.406,"fga":6.09,"fgm":2.47,"ft_pct":0.893,"fta":0.51,"ftm":0.45,"games_played":55,"seconds":1096.0,"oreb":0.24,"pf":1.53,"player_id":641,"pts":6.78,"reb":2.47,"season":1999,"stl":0.35,"turnover":0.65},{"ast":2.25,"blk":0.01,"dreb":1.11,"fg3_pct":0.362,"fg3a":2.26,"fg3m":0.82,"fg_pct":0.383,"fga":5.74,"fgm":2.19,"ft_pct":0.849,"fta":0.74,"ftm":0.63,"games_played":72,"seconds":1076.0,"oreb":0.32,"pf":1.1,"player_id":1182,"pts":5.83,"reb":1.43,"season":1999,"stl":0.57,"turnover":0.92},{"ast":3.13,"blk":0.03,"dreb":1.73,"fg3_pct":0.414,"fg3a":0.97,"fg3m":0.4,"fg_pct":0.434,"fga":5.3,"fgm":2.3,"ft_pct":0.781,"fta":2.43,"ftm":1.9,"games_played":30,"seconds":1001.0,"oreb":0.53,"pf":1.07,"player_id":1063,"pts":6.9,"reb":2.27,"season":1999,"stl":0.77,"turnover":1.0}]}
