{"data":[{"player_id":830,"team_id":17},{"player_id":1437,"team_id":17},{"player_id":1116,"team_id":17},{"player_id":1287,"team_id":17},{"player_id":1436,"team_id":17},{"player_id":816,"team_id":17},{"player_id":1084,"team_id":17},{"player_id":3057,"team_id":17},{"player_id":1465,"team_id":17},{"player_id":1468,"team_id":17},{"player_id":954,"team_id":17},{"player_id":1438,"team_id":17},{"player_id":842,"team_id":17},{"player_id":1305,"team_id":17},{"player_id":1036,"team_id":17},{"player_id":1286,"team_id":17}]}
