{"data": [{"games_played": 68, "player_id": 561, "season": 1990, "min": "14:06", "fgm": 1.91, "fga": 4.07, "fg3m": 0.01, "fg3a": 0.13, "ftm": 0.87, "fta": 1.28, "oreb": 0.32, "dreb": 0.81, "reb": 1.13, "ast": 3.38, "stl": 0.69, "blk": 0.06, "turnover": 1.09, "pf": 0.91, "pts": 4.71, "fg_pct": 0.469, "fg3_pct": 0.111, "ft_pct": 0.678}, {"games_played": 63, "player_id": 2980, "season": 1990, "min": "16:09", "fgm": 1.35, "fga": 2.68, "fg3m": 0.0, "fg3a": 0.03, "ftm": 1.1, "fta": 1.49, "oreb": 0.97, "dreb": 2.54, "reb": 3.51, "ast": 0.83, "stl": 0.46, "blk": 0.4, "turnover": 1.13, "pf": 2.73, "pts": 3.79, "fg_pct": 0.503, "fg3_pct": 0.0, "ft_pct": 0.734}, {"games_played": 82, "player_id": 2981, "season": 1990, "min": "37:44", "fgm": 9.2, "fga": 16.66, "fg3m": 0.01, "fg3a": 0.09, "ftm": 7.22, "fta": 9.48, "oreb": 4.09, "dreb": 8.88, "reb": 12.96, "ast": 2.54, "stl": 1.55, "blk": 3.9, "turnover": 3.29, "pf": 3.22, "pts": 25.62, "fg_pct": 0.552, "fg3_pct": 0.143, "ft_pct": 0.762}, {"games_played": 70, "player_id": 2982, "season": 1990, "min": "24:02", "fgm": 2.87, "fga": 6.09, "fg3m": 0.23, "fg3a": 0.81, "ftm": 1.57, "fta": 1.9, "oreb": 0.71, "dreb": 1.8, "reb": 2.51, "ast": 3.87, "stl": 0.9, "blk": 0.46, "turnover": 1.86, "pf": 2.49, "pts": 7.54, "fg_pct": 0.472, "fg3_pct": 0.281, "ft_pct": 0.827}, {"games_played": 82, "player_id": 2984, "season": 1990, "min": "37:07", "fgm": 5.83, "fga": 11.9, "fg3m": 0.24, "fg3a": 0.78, "ftm": 3.96, "fta": 4.9, "oreb": 1.73, "dreb": 3.83, "reb": 5.56, "ast": 2.9, "stl": 0.84, "blk": 0.4, "turnover": 1.79, "pf": 2.32, "pts": 15.87, "fg_pct": 0.49, "fg3_pct": 0.312, "ft_pct": 0.808}, {"games_played": 50, "player_id": 2985, "season": 1990, "min": "9:16", "fgm": 1.94, "fga": 4.24, "fg3m": 0.06, "fg3a": 0.38, "ftm": 0.56, "fta": 0.66, "oreb": 0.36, "dreb": 0.9, "reb": 1.26, "ast": 0.7, "stl": 0.16, "blk": 0.02, "turnover": 0.98, "pf": 1.06, "pts": 4.5, "fg_pct": 0.458, "fg3_pct": 0.158, "ft_pct": 0.848}, {"games_played": 66, "player_id": 2986, "season": 1990, "min": "16:39", "fgm": 2.68, "fga": 5.82, "fg3m": 0.0, "fg3a": 0.05, "ftm": 1.35, "fta": 1.59, "oreb": 1.48, "dreb": 3.26, "reb": 4.74, "ast": 0.79, "stl": 0.48, "blk": 0.2, "turnover": 1.35, "pf": 2.61, "pts": 6.71, "fg_pct": 0.461, "fg3_pct": 0.0, "ft_pct": 0.848}, {"games_played": 67, "player_id": 2987, "season": 1990, "min": "32:45", "fgm": 7.51, "fga": 15.51, "fg3m": 0.1, "fg3a": 0.49, "ftm": 2.45, "fta": 3.58, "oreb": 2.9, "dreb": 4.88, "reb": 7.78, "ast": 2.34, "stl": 0.91, "blk": 0.45, "turnover": 1.96, "pf": 3.36, "pts": 17.57, "fg_pct": 0.484, "fg3_pct": 0.212, "ft_pct": 0.683}, {"games_played": 35, "player_id": 2988, "season": 1990, "min": "4:36", "fgm": 0.77, "fga": 1.71, "fg3m": 0.0, "fg3a": 0.0, "ftm": 0.8, "fta": 1.29, "oreb": 0.66, "dreb": 1.0, "reb": 1.66, "ast": 0.11, "stl": 0.11, "blk": 0.26, "turnover": 0.37, "pf": 0.74, "pts": 2.34, "fg_pct": 0.45, "fg3_pct": 0, "ft_pct": 0.622}, {"games_played": 12, "player_id": 3016, "season": 1990, "min": "12:55", "fgm": 1.17, "fga": 2.83, "fg3m": 0.0, "fg3a": 0.0, "ftm": 0.67, "fta": 0.75, "oreb": 0.0, "dreb": 1.0, "reb": 1.0, "ast": 1.58, "stl": 0.17, "blk": 0.0, "turnover": 1.08, "pf": 1.25, "pts": 3.0, "fg_pct": 0.412, "fg3_pct": 0, "ft_pct": 0.889}, {"games_played": 42, "player_id": 3017, "season": 1990, "min": "9:28", "fgm": 1.62, "fga": 3.69, "fg3m": 0.0, "fg3a": 0.05, "ftm": 0.52, "fta": 0.95, "oreb": 0.67, "dreb": 2.21, "reb": 2.88, "ast": 0.4, "stl": 0.05, "blk": 0.69, "turnover": 0.81, "pf": 1.52, "pts": 3.76, "fg_pct": 0.439, "fg3_pct": 0.0, "ft_pct": 0.55}, {"games_played": 58, "player_id": 3022, "season": 1990, "min": "35:47", "fgm": 5.41, "fga": 11.22, "fg3m": 0.19, "fg3a": 0.57, "ftm": 2.78, "fta": 3.64, "oreb": 0.98, "dreb": 2.79, "reb": 3.78, "ast": 7.98, "stl": 2.02, "blk": 0.19, "turnover": 2.69, "pf": 2.16, "pts": 13.79, "fg_pct": 0.482, "fg3_pct": 0.333, "ft_pct": 0.763}, {"games_played": 75, "player_id": 3039, "season": 1990, "min": "34:33", "fgm": 6.04, "fga": 13.21, "fg3m": 0.09, "fg3a": 0.47, "ftm": 2.27, "fta": 2.84, "oreb": 0.91, "dreb": 3.77, "reb": 4.68, "ast": 4.77, "stl": 1.05, "blk": 0.61, "turnover": 2.23, "pf": 3.01, "pts": 14.44, "fg_pct": 0.457, "fg3_pct": 0.2, "ft_pct": 0.798}, {"games_played": 8, "player_id": 3050, "season": 1990, "min": "12:52", "fgm": 1.25, "fga": 2.88, "fg3m": 0.0, "fg3a": 0.13, "ftm": 1.13, "fta": 1.38, "oreb": 0.25, "dreb": 2.0, "reb": 2.25, "ast": 1.75, "stl": 0.38, "blk": 0.38, "turnover": 1.75, "pf": 1.75, "pts": 3.63, "fg_pct": 0.435, "fg3_pct": 0.0, "ft_pct": 0.818}, {"games_played": 7, "player_id": 3072, "season": 1990, "min": "14:08", "fgm": 2.0, "fga": 4.14, "fg3m": 0.0, "fg3a": 0.14, "ftm": 0.86, "fta": 1.29, "oreb": 0.14, "dreb": 0.86, "reb": 1.0, "ast": 1.0, "stl": 0.29, "blk": 0.14, "turnover": 1.14, "pf": 1.29, "pts": 4.86, "fg_pct": 0.483, "fg3_pct": 0.0, "ft_pct": 0.667}, {"games_played": 25, "player_id": 3081, "season": 1990, "min": "22:31", "fgm": 2.12, "fga": 5.52, "fg3m": 0.04, "fg3a": 0.36, "ftm": 1.16, "fta": 1.64, "oreb": 0.96, "dreb": 2.04, "reb": 3.0, "ast": 1.84, "stl": 0.76, "blk": 0.2, "turnover": 1.68, "pf": 2.64, "pts": 5.44, "fg_pct": 0.384, "fg3_pct": 0.111, "ft_pct": 0.707}]}