{"data": [{"games_played": 9, "player_id": 640, "season": 1990, "min": "10:06", "fgm": 2.22, "fga": 4.33, "fg3m": 0.0, "fg3a": 0.0, "ftm": 0.11, "fta": 0.33, "oreb": 0.67, "dreb": 1.44, "reb": 2.11, "ast": 0.44, "stl": 0.0, "blk": 0.33, "turnover": 0.67, "pf": 1.56, "pts": 4.56, "fg_pct": 0.513, "fg3_pct": 0, "ft_pct": 0.333}, {"games_played": 61, "player_id": 2893, "season": 1990, "min": "25:34", "fgm": 2.79, "fga": 6.84, "fg3m": 0.0, "fg3a": 0.0, "ftm": 1.54, "fta": 2.89, "oreb": 3.75, "dreb": 4.62, "reb": 8.38, "ast": 0.61, "stl": 0.64, "blk": 2.51, "turnover": 1.31, "pf": 3.56, "pts": 7.11, "fg_pct": 0.408, "fg3_pct": 0, "ft_pct": 0.534}, {"games_played": 79, "player_id": 2894, "season": 1990, "min": "32:18", "fgm": 5.18, "fga": 12.18, "fg3m": 0.57, "fg3a": 2.27, "ftm": 2.27, "fta": 3.09, "oreb": 2.66, "dreb": 3.94, "reb": 6.59, "ast": 2.78, "stl": 1.75, "blk": 1.22, "turnover": 2.11, "pf": 3.14, "pts": 13.19, "fg_pct": 0.425, "fg3_pct": 0.251, "ft_pct": 0.734}, {"games_played": 74, "player_id": 2895, "season": 1990, "min": "35:09", "fgm": 6.95, "fga": 14.86, "fg3m": 0.18, "fg3a": 0.51, "ftm": 4.36, "fta": 5.97, "oreb": 3.64, "dreb": 6.62, "reb": 10.26, "ast": 2.2, "stl": 0.96, "blk": 1.34, "turnover": 2.93, "pf": 2.93, "pts": 18.43, "fg_pct": 0.467, "fg3_pct": 0.342, "ft_pct": 0.731}, {"games_played": 56, "player_id": 2896, "season": 1990, "min": "13:16", "fgm": 2.93, "fga": 7.04, "fg3m": 0.13, "fg3a": 0.5, "ftm": 1.61, "fta": 2.04, "oreb": 0.71, "dreb": 1.25, "reb": 1.96, "ast": 0.54, "stl": 0.34, "blk": 0.34, "turnover": 0.8, "pf": 1.57, "pts": 7.59, "fg_pct": 0.416, "fg3_pct": 0.25, "ft_pct": 0.789}, {"games_played": 78, "player_id": 2897, "season": 1990, "min": "15:06", "fgm": 2.06, "fga": 4.4, "fg3m": 0.0, "fg3a": 0.0, "ftm": 1.44, "fta": 2.32, "oreb": 1.79, "dreb": 2.77, "reb": 4.56, "ast": 0.4, "stl": 0.26, "blk": 0.27, "turnover": 0.81, "pf": 2.55, "pts": 5.56, "fg_pct": 0.469, "fg3_pct": 0, "ft_pct": 0.619}, {"games_played": 74, "player_id": 2898, "season": 1990, "min": "11:36", "fgm": 1.27, "fga": 3.05, "fg3m": 0.01, "fg3a": 0.05, "ftm": 0.58, "fta": 0.89, "oreb": 0.82, "dreb": 1.08, "reb": 1.91, "ast": 0.69, "stl": 0.45, "blk": 0.2, "turnover": 0.35, "pf": 1.07, "pts": 3.14, "fg_pct": 0.416, "fg3_pct": 0.25, "ft_pct": 0.652}, {"games_played": 48, "player_id": 2899, "season": 1990, "min": "5:31", "fgm": 0.4, "fga": 1.48, "fg3m": 0.06, "fg3a": 0.31, "ftm": 0.52, "fta": 0.58, "oreb": 0.15, "dreb": 0.48, "reb": 0.63, "ast": 0.71, "stl": 0.23, "blk": 0.04, "turnover": 0.42, "pf": 0.81, "pts": 1.38, "fg_pct": 0.268, "fg3_pct": 0.2, "ft_pct": 0.893}, {"games_played": 72, "player_id": 2901, "season": 1990, "min": "35:54", "fgm": 6.0, "fga": 14.43, "fg3m": 0.19, "fg3a": 1.26, "ftm": 1.93, "fta": 2.44, "oreb": 0.93, "dreb": 2.53, "reb": 3.46, "ast": 6.13, "stl": 2.35, "blk": 0.56, "turnover": 2.88, "pf": 2.5, "pts": 14.13, "fg_pct": 0.416, "fg3_pct": 0.154, "ft_pct": 0.79}, {"games_played": 81, "player_id": 2902, "season": 1990, "min": "36:28", "fgm": 7.2, "fga": 15.4, "fg3m": 0.64, "fg3a": 1.78, "ftm": 3.6, "fta": 4.23, "oreb": 0.85, "dreb": 1.98, "reb": 2.83, "ast": 4.67, "stl": 1.05, "blk": 0.43, "turnover": 3.11, "pf": 2.85, "pts": 18.64, "fg_pct": 0.468, "fg3_pct": 0.361, "ft_pct": 0.851}, {"games_played": 62, "player_id": 2903, "season": 1990, "min": "30:54", "fgm": 5.06, "fga": 11.66, "fg3m": 0.06, "fg3a": 0.35, "ftm": 2.73, "fta": 3.73, "oreb": 2.84, "dreb": 4.9, "reb": 7.74, "ast": 2.37, "stl": 0.69, "blk": 1.45, "turnover": 2.27, "pf": 2.82, "pts": 12.92, "fg_pct": 0.434, "fg3_pct": 0.182, "ft_pct": 0.732}, {"games_played": 56, "player_id": 2904, "season": 1990, "min": "10:36", "fgm": 1.43, "fga": 3.45, "fg3m": 0.0, "fg3a": 0.04, "ftm": 0.57, "fta": 0.71, "oreb": 0.34, "dreb": 0.5, "reb": 0.84, "ast": 1.86, "stl": 0.45, "blk": 0.09, "turnover": 0.75, "pf": 1.04, "pts": 3.43, "fg_pct": 0.415, "fg3_pct": 0.0, "ft_pct": 0.8}, {"games_played": 61, "player_id": 3027, "season": 1990, "min": "16:38", "fgm": 3.98, "fga": 8.08, "fg3m": 0.38, "fg3a": 1.07, "ftm": 1.87, "fta": 2.25, "oreb": 0.84, "dreb": 0.97, "reb": 1.8, "ast": 1.41, "stl": 0.7, "blk": 0.02, "turnover": 1.33, "pf": 2.16, "pts": 10.21, "fg_pct": 0.493, "fg3_pct": 0.354, "ft_pct": 0.832}, {"games_played": 55, "player_id": 3045, "season": 1990, "min": "14:53", "fgm": 2.44, "fga": 5.24, "fg3m": 0.0, "fg3a": 0.07, "ftm": 0.85, "fta": 1.2, "oreb": 1.49, "dreb": 2.67, "reb": 4.16, "ast": 0.6, "stl": 0.64, "blk": 0.53, "turnover": 0.78, "pf": 1.82, "pts": 5.73, "fg_pct": 0.465, "fg3_pct": 0.0, "ft_pct": 0.712}]}