{"data": [{"games_played": 60, "player_id": 610, "season": 1991, "min": "22:30", "fgm": 3.37, "fga": 8.32, "fg3m": 0.32, "fg3a": 1.0, "ftm": 0.92, "fta": 1.42, "oreb": 1.12, "dreb": 1.92, "reb": 3.03, "ast": 2.42, "stl": 0.68, "blk": 0.23, "turnover": 1.23, "pf": 1.55, "pts": 7.97, "fg_pct": 0.405, "fg3_pct": 0.317, "ft_pct": 0.647}, {"games_played": 67, "player_id": 650, "season": 1991, "min": "8:58", "fgm": 1.39, "fga": 3.58, "fg3m": 0.39, "fg3a": 1.33, "ftm": 0.51, "fta": 0.67, "oreb": 0.09, "dreb": 0.61, "reb": 0.7, "ast": 1.36, "stl": 0.39, "blk": 0.13, "turnover": 1.04, "pf": 1.66, "pts": 3.67, "fg_pct": 0.388, "fg3_pct": 0.292, "ft_pct": 0.756}, {"games_played": 33, "player_id": 651, "season": 1991, "min": "4:00", "fgm": 0.67, "fga": 1.21, "fg3m": 0.0, "fg3a": 0.0, "ftm": 0.12, "fta": 0.39, "oreb": 0.42, "dreb": 0.67, "reb": 1.09, "ast": 0.09, "stl": 0.06, "blk": 0.18, "turnover": 0.24, "pf": 0.88, "pts": 1.45, "fg_pct": 0.55, "fg3_pct": 0, "ft_pct": 0.308}, {"games_played": 60, "player_id": 708, "season": 1991, "min": "11:58", "fgm": 1.33, "fga": 2.97, "fg3m": 0.0, "fg3a": 0.0, "ftm": 1.53, "fta": 2.22, "oreb": 1.08, "dreb": 0.98, "reb": 2.07, "ast": 0.57, "stl": 0.42, "blk": 0.12, "turnover": 0.65, "pf": 1.22, "pts": 4.2, "fg_pct": 0.449, "fg3_pct": 0, "ft_pct": 0.692}, {"games_played": 1, "player_id": 721, "season": 1991, "min": "1:00", "fgm": 0.0, "fga": 0.0, "fg3m": 0.0, "fg3a": 0.0, "ftm": 0.0, "fta": 0.0, "oreb": 1.0, "dreb": 0.0, "reb": 1.0, "ast": 0.0, "stl": 0.0, "blk": 0.0, "turnover": 0.0, "pf": 0.0, "pts": 0.0, "fg_pct": 0, "fg3_pct": 0, "ft_pct": 0}, {"games_played": 40, "player_id": 2912, "season": 1991, "min": "13:43", "fgm": 1.48, "fga": 3.58, "fg3m": 0.03, "fg3a": 0.1, "ftm": 0.45, "fta": 0.65, "oreb": 0.3, "dreb": 1.1, "reb": 1.4, "ast": 2.45, "stl": 0.9, "blk": 0.1, "turnover": 1.1, "pf": 1.35, "pts": 3.43, "fg_pct": 0.413, "fg3_pct": 0.25, "ft_pct": 0.692}, {"games_played": 81, "player_id": 2914, "season": 1991, "min": "23:02", "fgm": 4.43, "fga": 9.04, "fg3m": 0.01, "fg3a": 0.06, "ftm": 2.0, "fta": 2.62, "oreb": 1.58, "dreb": 2.69, "reb": 4.27, "ast": 0.78, "stl": 0.4, "blk": 1.19, "turnover": 1.41, "pf": 3.26, "pts": 10.88, "fg_pct": 0.49, "fg3_pct": 0.2, "ft_pct": 0.764}, {"games_played": 24, "player_id": 2978, "season": 1991, "min": "17:17", "fgm": 2.5, "fga": 5.38, "fg3m": 0.79, "fg3a": 2.0, "ftm": 0.67, "fta": 0.83, "oreb": 0.33, "dreb": 1.21, "reb": 1.54, "ast": 1.13, "stl": 0.88, "blk": 0.13, "turnover": 0.58, "pf": 1.63, "pts": 6.46, "fg_pct": 0.465, "fg3_pct": 0.396, "ft_pct": 0.8}, {"games_played": 68, "player_id": 2981, "season": 1991, "min": "37:42", "fgm": 8.71, "fga": 15.79, "fg3m": 0.01, "fg3a": 0.12, "ftm": 5.78, "fta": 8.25, "oreb": 3.84, "dreb": 8.35, "reb": 12.19, "ast": 2.66, "stl": 2.32, "blk": 4.49, "turnover": 2.68, "pf": 3.22, "pts": 23.21, "fg_pct": 0.551, "fg3_pct": 0.125, "ft_pct": 0.701}, {"games_played": 56, "player_id": 2982, "season": 1991, "min": "13:33", "fgm": 1.07, "fga": 2.88, "fg3m": 0.05, "fg3a": 0.38, "ftm": 0.5, "fta": 0.73, "oreb": 0.39, "dreb": 1.3, "reb": 1.7, "ast": 2.54, "stl": 0.52, "blk": 0.34, "turnover": 1.14, "pf": 1.54, "pts": 2.7, "fg_pct": 0.373, "fg3_pct": 0.143, "ft_pct": 0.683}, {"games_played": 82, "player_id": 2984, "season": 1991, "min": "38:02", "fgm": 6.27, "fga": 12.68, "fg3m": 0.3, "fg3a": 1.0, "ftm": 3.48, "fta": 4.04, "oreb": 1.74, "dreb": 3.61, "reb": 5.35, "ast": 2.61, "stl": 1.02, "blk": 0.35, "turnover": 1.85, "pf": 1.82, "pts": 16.32, "fg_pct": 0.494, "fg3_pct": 0.305, "ft_pct": 0.861}, {"games_played": 80, "player_id": 2986, "season": 1991, "min": "14:05", "fgm": 1.84, "fga": 4.3, "fg3m": 0.0, "fg3a": 0.0, "ftm": 0.91, "fta": 1.11, "oreb": 1.15, "dreb": 3.13, "reb": 4.28, "ast": 0.45, "stl": 0.36, "blk": 0.14, "turnover": 0.78, "pf": 1.85, "pts": 4.59, "fg_pct": 0.427, "fg3_pct": 0, "ft_pct": 0.82}, {"games_played": 70, "player_id": 2987, "season": 1991, "min": "30:42", "fgm": 7.34, "fga": 15.04, "fg3m": 0.07, "fg3a": 0.19, "ftm": 2.53, "fta": 3.56, "oreb": 3.53, "dreb": 5.49, "reb": 9.01, "ast": 1.46, "stl": 0.83, "blk": 0.49, "turnover": 1.64, "pf": 3.0, "pts": 17.29, "fg_pct": 0.488, "fg3_pct": 0.385, "ft_pct": 0.711}, {"games_played": 57, "player_id": 3022, "season": 1991, "min": "36:01", "fgm": 5.26, "fga": 11.56, "fg3m": 0.09, "fg3a": 0.26, "ftm": 3.19, "fta": 4.65, "oreb": 1.61, "dreb": 3.04, "reb": 4.65, "ast": 8.61, "stl": 2.07, "blk": 0.3, "turnover": 2.81, "pf": 2.14, "pts": 13.81, "fg_pct": 0.455, "fg3_pct": 0.333, "ft_pct": 0.687}, {"games_played": 57, "player_id": 3039, "season": 1991, "min": "33:08", "fgm": 5.47, "fga": 12.02, "fg3m": 0.23, "fg3a": 0.98, "ftm": 1.88, "fta": 2.42, "oreb": 1.09, "dreb": 4.18, "reb": 5.26, "ast": 5.3, "stl": 0.95, "blk": 0.89, "turnover": 2.46, "pf": 2.65, "pts": 13.05, "fg_pct": 0.455, "fg3_pct": 0.232, "ft_pct": 0.775}]}