{"data": [{"games_played": 43, "player_id": 12, "season": 2018, "min": "29:48", "fgm": 3.49, "fga": 6.42, "fg3m": 0.21, "fg3a": 0.79, "ftm": 0.86, "fta": 1.49, "oreb": 1.12, "dreb": 4.72, "reb": 5.84, "ast": 2.98, "stl": 1.26, "blk": 0.86, "turnover": 1.35, "pf": 2.6, "pts": 8.05, "fg_pct": 0.543, "fg3_pct": 0.265, "ft_pct": 0.578}, {"games_played": 18, "player_id": 66, "season": 2018, "min": "18:19", "fgm": 2.72, "fga": 6.78, "fg3m": 0.83, "fg3a": 2.22, "ftm": 1.22, "fta": 1.67, "oreb": 0.5, "dreb": 1.22, "reb": 1.72, "ast": 0.89, "stl": 0.56, "blk": 0.22, "turnover": 1.06, "pf": 2.78, "pts": 7.5, "fg_pct": 0.402, "fg3_pct": 0.375, "ft_pct": 0.733}, {"games_played": 29, "player_id": 67, "season": 2018, "min": "13:20", "fgm": 2.62, "fga": 5.83, "fg3m": 0.52, "fg3a": 1.86, "ftm": 0.79, "fta": 1.14, "oreb": 0.41, "dreb": 1.14, "reb": 1.55, "ast": 0.86, "stl": 0.31, "blk": 0.14, "turnover": 0.72, "pf": 1.14, "pts": 6.55, "fg_pct": 0.45, "fg3_pct": 0.278, "ft_pct": 0.697}, {"games_played": 45, "player_id": 87, "season": 2018, "min": "12:48", "fgm": 1.24, "fga": 4.11, "fg3m": 0.76, "fg3a": 2.27, "ftm": 0.58, "fta": 0.71, "oreb": 0.31, "dreb": 1.16, "reb": 1.47, "ast": 1.53, "stl": 0.58, "blk": 0.22, "turnover": 0.73, "pf": 1.22, "pts": 3.82, "fg_pct": 0.303, "fg3_pct": 0.333, "ft_pct": 0.813}, {"games_played": 36, "player_id": 90, "season": 2018, "min": "14:27", "fgm": 2.39, "fga": 4.47, "fg3m": 0.42, "fg3a": 1.19, "ftm": 1.08, "fta": 1.61, "oreb": 0.47, "dreb": 2.72, "reb": 3.19, "ast": 0.72, "stl": 0.56, "blk": 0.25, "turnover": 0.64, "pf": 0.97, "pts": 6.28, "fg_pct": 0.534, "fg3_pct": 0.349, "ft_pct": 0.672}, {"games_played": 72, "player_id": 104, "season": 2018, "min": "32:31", "fgm": 6.81, "fga": 15.56, "fg3m": 2.15, "fg3a": 5.92, "ftm": 4.76, "fta": 5.64, "oreb": 0.54, "dreb": 2.76, "reb": 3.31, "ast": 6.24, "stl": 1.31, "blk": 0.31, "turnover": 1.81, "pf": 1.71, "pts": 20.53, "fg_pct": 0.437, "fg3_pct": 0.364, "ft_pct": 0.845}, {"games_played": 79, "player_id": 169, "season": 2018, "min": "30:50", "fgm": 4.94, "fga": 11.01, "fg3m": 1.25, "fg3a": 3.46, "ftm": 2.43, "fta": 3.2, "oreb": 1.04, "dreb": 6.92, "reb": 7.96, "ast": 4.42, "stl": 1.06, "blk": 1.1, "turnover": 1.96, "pf": 2.75, "pts": 13.56, "fg_pct": 0.448, "fg3_pct": 0.363, "ft_pct": 0.759}, {"games_played": 65, "player_id": 187, "season": 2018, "min": "21:05", "fgm": 3.54, "fga": 7.32, "fg3m": 1.09, "fg3a": 2.71, "ftm": 1.23, "fta": 1.55, "oreb": 1.62, "dreb": 4.69, "reb": 6.31, "ast": 0.77, "stl": 0.68, "blk": 0.52, "turnover": 1.34, "pf": 2.97, "pts": 9.4, "fg_pct": 0.483, "fg3_pct": 0.403, "ft_pct": 0.792}, {"games_played": 82, "player_id": 215, "season": 2018, "min": "31:47", "fgm": 3.66, "fga": 9.48, "fg3m": 1.98, "fg3a": 5.67, "ftm": 1.16, "fta": 1.29, "oreb": 0.56, "dreb": 3.38, "reb": 3.94, "ast": 1.78, "stl": 1.48, "blk": 0.44, "turnover": 1.27, "pf": 2.01, "pts": 10.45, "fg_pct": 0.386, "fg3_pct": 0.348, "ft_pct": 0.896}, {"games_played": 58, "player_id": 231, "season": 2018, "min": "26:06", "fgm": 5.14, "fga": 10.17, "fg3m": 0.88, "fg3a": 2.45, "ftm": 2.6, "fta": 3.4, "oreb": 1.28, "dreb": 3.43, "reb": 4.71, "ast": 1.12, "stl": 0.9, "blk": 1.41, "turnover": 1.69, "pf": 3.79, "pts": 13.76, "fg_pct": 0.505, "fg3_pct": 0.359, "ft_pct": 0.766}, {"games_played": 77, "player_id": 291, "season": 2018, "min": "16:11", "fgm": 2.12, "fga": 5.23, "fg3m": 0.6, "fg3a": 1.69, "ftm": 0.75, "fta": 1.09, "oreb": 0.23, "dreb": 1.12, "reb": 1.35, "ast": 2.38, "stl": 0.61, "blk": 0.05, "turnover": 0.86, "pf": 1.09, "pts": 5.58, "fg_pct": 0.404, "fg3_pct": 0.354, "ft_pct": 0.69}, {"games_played": 26, "player_id": 364, "season": 2018, "min": "19:04", "fgm": 2.62, "fga": 7.0, "fg3m": 1.12, "fg3a": 3.62, "ftm": 0.85, "fta": 0.96, "oreb": 0.15, "dreb": 2.54, "reb": 2.69, "ast": 1.65, "stl": 0.73, "blk": 0.19, "turnover": 1.23, "pf": 1.69, "pts": 7.19, "fg_pct": 0.374, "fg3_pct": 0.309, "ft_pct": 0.88}, {"games_played": 51, "player_id": 385, "season": 2018, "min": "14:07", "fgm": 2.27, "fga": 4.16, "fg3m": 0.06, "fg3a": 0.29, "ftm": 0.96, "fta": 1.35, "oreb": 1.37, "dreb": 2.67, "reb": 4.04, "ast": 1.06, "stl": 0.33, "blk": 0.27, "turnover": 0.69, "pf": 1.76, "pts": 5.57, "fg_pct": 0.547, "fg3_pct": 0.2, "ft_pct": 0.71}, {"games_played": 1, "player_id": 430, "season": 2018, "min": "6:44", "fgm": 1.0, "fga": 2.0, "fg3m": 0.0, "fg3a": 0.0, "ftm": 0.0, "fta": 0.0, "oreb": 0.0, "dreb": 0.0, "reb": 0.0, "ast": 0.0, "stl": 1.0, "blk": 0.0, "turnover": 1.0, "pf": 0.0, "pts": 2.0, "fg_pct": 0.5, "fg3_pct": 0, "ft_pct": 0}, {"games_played": 75, "player_id": 436, "season": 2018, "min": "27:12", "fgm": 2.77, "fga": 6.56, "fg3m": 1.2, "fg3a": 3.52, "ftm": 1.07, "fta": 1.43, "oreb": 0.37, "dreb": 2.51, "reb": 2.88, "ast": 1.4, "stl": 1.03, "blk": 0.4, "turnover": 0.93, "pf": 2.72, "pts": 7.81, "fg_pct": 0.423, "fg3_pct": 0.341, "ft_pct": 0.748}, {"games_played": 22, "player_id": 470, "season": 2018, "min": "7:55", "fgm": 0.68, "fga": 2.32, "fg3m": 0.09, "fg3a": 0.73, "ftm": 0.32, "fta": 0.45, "oreb": 0.18, "dreb": 1.23, "reb": 1.41, "ast": 0.36, "stl": 0.18, "blk": 0.05, "turnover": 0.27, "pf": 0.5, "pts": 1.77, "fg_pct": 0.294, "fg3_pct": 0.125, "ft_pct": 0.7}, {"games_played": 43, "player_id": 1771, "season": 2018, "min": "16:06", "fgm": 2.56, "fga": 4.95, "fg3m": 0.0, "fg3a": 0.02, "ftm": 1.81, "fta": 2.53, "oreb": 1.35, "dreb": 4.19, "reb": 5.53, "ast": 2.07, "stl": 0.47, "blk": 0.72, "turnover": 1.16, "pf": 2.23, "pts": 6.93, "fg_pct": 0.516, "fg3_pct": 0.0, "ft_pct": 0.716}, {"games_played": 34, "player_id": 2099, "season": 2018, "min": "23:31", "fgm": 2.82, "fga": 6.62, "fg3m": 1.41, "fg3a": 3.82, "ftm": 1.24, "fta": 1.47, "oreb": 1.24, "dreb": 3.41, "reb": 4.65, "ast": 1.47, "stl": 0.41, "blk": 0.97, "turnover": 1.12, "pf": 2.38, "pts": 8.29, "fg_pct": 0.427, "fg3_pct": 0.369, "ft_pct": 0.84}, {"games_played": 20, "player_id": 3943, "season": 2018, "min": "12:41", "fgm": 0.8, "fga": 2.4, "fg3m": 0.25, "fg3a": 1.2, "ftm": 0.15, "fta": 0.2, "oreb": 0.4, "dreb": 1.65, "reb": 2.05, "ast": 0.7, "stl": 0.65, "blk": 0.1, "turnover": 0.35, "pf": 0.8, "pts": 2.0, "fg_pct": 0.333, "fg3_pct": 0.208, "ft_pct": 0.75}, {"games_played": 3, "player_id": 2116373, "season": 2018, "min": "8:38", "fgm": 1.0, "fga": 4.0, "fg3m": 0.0, "fg3a": 1.67, "ftm": 0.67, "fta": 0.67, "oreb": 0.0, "dreb": 0.33, "reb": 0.33, "ast": 1.67, "stl": 0.33, "blk": 0.0, "turnover": 0.33, "pf": 0.33, "pts": 2.67, "fg_pct": 0.25, "fg3_pct": 0.0, "ft_pct": 1.0}]}