{"data": [{"games_played": 6, "player_id": 814, "season": 2000, "min": "8:17", "fgm": 0.67, "fga": 1.83, "fg3m": 0.33, "fg3a": 0.83, "ftm": 0.0, "fta": 0.0, "oreb": 0.0, "dreb": 1.33, "reb": 1.33, "ast": 0.0, "stl": 0.67, "blk": 0.17, "turnover": 0.67, "pf": 0.83, "pts": 1.67, "fg_pct": 0.364, "fg3_pct": 0.4, "ft_pct": 0}, {"games_played": 80, "player_id": 866, "season": 2000, "min": "31:43", "fgm": 2.83, "fga": 4.6, "fg3m": 0.01, "fg3a": 0.03, "ftm": 1.61, "fta": 2.81, "oreb": 2.64, "dreb": 5.1, "reb": 7.74, "ast": 2.81, "stl": 1.31, "blk": 1.71, "turnover": 1.76, "pf": 3.01, "pts": 7.28, "fg_pct": 0.614, "fg3_pct": 0.5, "ft_pct": 0.573}, {"games_played": 4, "player_id": 879, "season": 2000, "min": "33:03", "fgm": 4.75, "fga": 10.75, "fg3m": 0.25, "fg3a": 0.25, "ftm": 4.0, "fta": 6.5, "oreb": 2.0, "dreb": 4.25, "reb": 6.25, "ast": 6.25, "stl": 1.25, "blk": 0.5, "turnover": 2.75, "pf": 2.25, "pts": 13.75, "fg_pct": 0.442, "fg3_pct": 1.0, "ft_pct": 0.615}, {"games_played": 82, "player_id": 910, "season": 2000, "min": "14:44", "fgm": 1.98, "fga": 4.44, "fg3m": 0.01, "fg3a": 0.16, "ftm": 1.04, "fta": 1.62, "oreb": 1.05, "dreb": 1.91, "reb": 2.96, "ast": 0.96, "stl": 0.35, "blk": 0.2, "turnover": 1.04, "pf": 1.66, "pts": 5.0, "fg_pct": 0.445, "fg3_pct": 0.077, "ft_pct": 0.639}, {"games_played": 75, "player_id": 933, "season": 2000, "min": "36:59", "fgm": 5.51, "fga": 13.36, "fg3m": 1.91, "fg3a": 5.37, "ftm": 2.93, "fta": 3.32, "oreb": 1.25, "dreb": 3.32, "reb": 4.57, "ast": 6.99, "stl": 1.8, "blk": 0.17, "turnover": 2.67, "pf": 2.07, "pts": 15.85, "fg_pct": 0.412, "fg3_pct": 0.355, "ft_pct": 0.884}, {"games_played": 82, "player_id": 968, "season": 2000, "min": "20:51", "fgm": 2.89, "fga": 7.22, "fg3m": 0.0, "fg3a": 0.09, "ftm": 2.15, "fta": 3.4, "oreb": 0.94, "dreb": 2.33, "reb": 3.27, "ast": 0.9, "stl": 0.34, "blk": 0.35, "turnover": 1.51, "pf": 2.13, "pts": 7.93, "fg_pct": 0.4, "fg3_pct": 0.0, "ft_pct": 0.631}, {"games_played": 65, "player_id": 977, "season": 2000, "min": "11:42", "fgm": 1.26, "fga": 2.23, "fg3m": 0.0, "fg3a": 0.0, "ftm": 0.71, "fta": 1.15, "oreb": 1.29, "dreb": 2.43, "reb": 3.72, "ast": 0.32, "stl": 0.35, "blk": 0.83, "turnover": 0.74, "pf": 2.92, "pts": 3.23, "fg_pct": 0.566, "fg3_pct": 0, "ft_pct": 0.613}, {"games_played": 26, "player_id": 981, "season": 2000, "min": "8:35", "fgm": 0.69, "fga": 2.15, "fg3m": 0.15, "fg3a": 0.62, "ftm": 0.46, "fta": 0.69, "oreb": 0.0, "dreb": 0.96, "reb": 0.96, "ast": 1.38, "stl": 0.62, "blk": 0.0, "turnover": 0.96, "pf": 1.12, "pts": 2.0, "fg_pct": 0.321, "fg3_pct": 0.25, "ft_pct": 0.667}, {"games_played": 67, "player_id": 995, "season": 2000, "min": "13:26", "fgm": 1.6, "fga": 2.88, "fg3m": 0.0, "fg3a": 0.0, "ftm": 0.7, "fta": 1.22, "oreb": 1.36, "dreb": 2.16, "reb": 3.52, "ast": 0.48, "stl": 0.61, "blk": 0.49, "turnover": 0.76, "pf": 2.96, "pts": 3.9, "fg_pct": 0.554, "fg3_pct": 0, "ft_pct": 0.573}, {"games_played": 77, "player_id": 1087, "season": 2000, "min": "40:10", "fgm": 10.23, "fga": 22.39, "fg3m": 0.77, "fg3a": 2.16, "ftm": 5.58, "fta": 7.62, "oreb": 2.49, "dreb": 5.04, "reb": 7.53, "ast": 4.57, "stl": 1.51, "blk": 1.53, "turnover": 2.57, "pf": 2.08, "pts": 26.82, "fg_pct": 0.457, "fg3_pct": 0.355, "ft_pct": 0.733}, {"games_played": 75, "player_id": 1113, "season": 2000, "min": "13:24", "fgm": 1.67, "fga": 4.96, "fg3m": 0.29, "fg3a": 1.45, "ftm": 1.13, "fta": 1.39, "oreb": 0.51, "dreb": 0.89, "reb": 1.4, "ast": 2.16, "stl": 0.49, "blk": 0.04, "turnover": 1.23, "pf": 1.09, "pts": 4.76, "fg_pct": 0.336, "fg3_pct": 0.202, "ft_pct": 0.817}, {"games_played": 77, "player_id": 1158, "season": 2000, "min": "18:07", "fgm": 2.86, "fga": 6.84, "fg3m": 0.0, "fg3a": 0.04, "ftm": 0.65, "fta": 0.77, "oreb": 0.91, "dreb": 2.64, "reb": 3.55, "ast": 0.84, "stl": 0.48, "blk": 0.53, "turnover": 0.77, "pf": 3.1, "pts": 6.36, "fg_pct": 0.417, "fg3_pct": 0.0, "ft_pct": 0.847}, {"games_played": 76, "player_id": 1176, "season": 2000, "min": "20:46", "fgm": 2.93, "fga": 7.58, "fg3m": 1.28, "fg3a": 2.95, "ftm": 1.12, "fta": 1.29, "oreb": 0.67, "dreb": 2.09, "reb": 2.76, "ast": 0.67, "stl": 0.53, "blk": 0.2, "turnover": 0.89, "pf": 3.17, "pts": 8.26, "fg_pct": 0.387, "fg3_pct": 0.433, "ft_pct": 0.867}, {"games_played": 82, "player_id": 1299, "season": 2000, "min": "29:08", "fgm": 4.49, "fga": 10.3, "fg3m": 1.8, "fg3a": 4.44, "ftm": 1.11, "fta": 1.56, "oreb": 0.8, "dreb": 3.18, "reb": 3.99, "ast": 1.71, "stl": 0.62, "blk": 0.23, "turnover": 1.18, "pf": 2.44, "pts": 11.89, "fg_pct": 0.436, "fg3_pct": 0.407, "ft_pct": 0.711}, {"games_played": 7, "player_id": 2850, "season": 2000, "min": "22:16", "fgm": 2.29, "fga": 6.29, "fg3m": 1.71, "fg3a": 4.57, "ftm": 0.57, "fta": 0.71, "oreb": 0.0, "dreb": 1.57, "reb": 1.57, "ast": 1.71, "stl": 0.57, "blk": 0.0, "turnover": 1.0, "pf": 1.43, "pts": 6.86, "fg_pct": 0.364, "fg3_pct": 0.375, "ft_pct": 0.8}]}