{"data": [{"games_played": 69, "player_id": 29, "season": 2017, "min": "23:14", "fgm": 4.39, "fga": 10.0, "fg3m": 1.67, "fg3a": 4.54, "ftm": 1.16, "fta": 1.48, "oreb": 0.22, "dreb": 2.7, "reb": 2.91, "ast": 6.29, "stl": 0.51, "blk": 0.04, "turnover": 2.07, "pf": 1.2, "pts": 11.61, "fg_pct": 0.439, "fg3_pct": 0.367, "ft_pct": 0.784}, {"games_played": 77, "player_id": 30, "season": 2017, "min": "34:12", "fgm": 6.97, "fga": 15.69, "fg3m": 1.55, "fg3a": 4.32, "ftm": 3.36, "fta": 4.06, "oreb": 1.0, "dreb": 5.08, "reb": 6.08, "ast": 1.97, "stl": 0.64, "blk": 0.18, "turnover": 1.53, "pf": 1.22, "pts": 18.86, "fg_pct": 0.445, "fg3_pct": 0.357, "ft_pct": 0.827}, {"games_played": 82, "player_id": 157, "season": 2017, "min": "27:49", "fgm": 3.79, "fga": 8.9, "fg3m": 1.63, "fg3a": 4.38, "ftm": 1.0, "fta": 1.26, "oreb": 0.32, "dreb": 2.72, "reb": 3.04, "ast": 2.45, "stl": 0.78, "blk": 0.11, "turnover": 0.95, "pf": 1.87, "pts": 10.22, "fg_pct": 0.426, "fg3_pct": 0.373, "ft_pct": 0.796}, {"games_played": 21, "player_id": 158, "season": 2017, "min": "21:20", "fgm": 2.19, "fga": 5.76, "fg3m": 0.95, "fg3a": 3.19, "ftm": 0.52, "fta": 0.71, "oreb": 1.05, "dreb": 2.52, "reb": 3.57, "ast": 1.24, "stl": 0.48, "blk": 0.19, "turnover": 1.0, "pf": 2.05, "pts": 5.86, "fg_pct": 0.38, "fg3_pct": 0.299, "ft_pct": 0.733}, {"games_played": 71, "player_id": 195, "season": 2017, "min": "18:52", "fgm": 2.63, "fga": 6.39, "fg3m": 1.11, "fg3a": 3.2, "ftm": 2.0, "fta": 2.39, "oreb": 0.17, "dreb": 1.62, "reb": 1.79, "ast": 2.14, "stl": 0.66, "blk": 0.17, "turnover": 1.07, "pf": 2.23, "pts": 8.38, "fg_pct": 0.412, "fg3_pct": 0.348, "ft_pct": 0.835}, {"games_played": 72, "player_id": 257, "season": 2017, "min": "16:45", "fgm": 2.1, "fga": 4.29, "fg3m": 0.56, "fg3a": 1.78, "ftm": 0.61, "fta": 0.82, "oreb": 0.99, "dreb": 2.26, "reb": 3.25, "ast": 0.71, "stl": 0.36, "blk": 0.65, "turnover": 0.42, "pf": 1.58, "pts": 5.36, "fg_pct": 0.489, "fg3_pct": 0.312, "ft_pct": 0.746}, {"games_played": 63, "player_id": 301, "season": 2017, "min": "33:49", "fgm": 4.49, "fga": 11.06, "fg3m": 2.43, "fg3a": 6.38, "ftm": 1.32, "fta": 1.6, "oreb": 0.44, "dreb": 2.7, "reb": 3.14, "ast": 2.73, "stl": 1.21, "blk": 0.25, "turnover": 1.32, "pf": 2.22, "pts": 12.73, "fg_pct": 0.406, "fg3_pct": 0.381, "ft_pct": 0.822}, {"games_played": 61, "player_id": 312, "season": 2017, "min": "11:56", "fgm": 1.44, "fga": 2.25, "fg3m": 0.0, "fg3a": 0.05, "ftm": 0.62, "fta": 1.08, "oreb": 1.39, "dreb": 2.64, "reb": 4.03, "ast": 0.57, "stl": 0.36, "blk": 1.1, "turnover": 0.64, "pf": 1.98, "pts": 3.51, "fg_pct": 0.642, "fg3_pct": 0.0, "ft_pct": 0.576}, {"games_played": 11, "player_id": 331, "season": 2017, "min": "15:58", "fgm": 3.64, "fga": 6.82, "fg3m": 0.09, "fg3a": 0.55, "ftm": 1.36, "fta": 2.55, "oreb": 1.27, "dreb": 3.18, "reb": 4.45, "ast": 0.64, "stl": 0.27, "blk": 0.18, "turnover": 0.82, "pf": 1.64, "pts": 8.73, "fg_pct": 0.533, "fg3_pct": 0.167, "ft_pct": 0.536}, {"games_played": 30, "player_id": 345, "season": 2017, "min": "15:43", "fgm": 1.83, "fga": 3.5, "fg3m": 0.0, "fg3a": 0.03, "ftm": 0.7, "fta": 0.93, "oreb": 1.6, "dreb": 4.0, "reb": 5.6, "ast": 0.67, "stl": 1.03, "blk": 0.73, "turnover": 0.87, "pf": 1.97, "pts": 4.37, "fg_pct": 0.524, "fg3_pct": 0.0, "ft_pct": 0.75}, {"games_played": 77, "player_id": 346, "season": 2017, "min": "24:40", "fgm": 4.49, "fga": 9.84, "fg3m": 1.79, "fg3a": 4.38, "ftm": 1.26, "fta": 1.4, "oreb": 0.29, "dreb": 5.4, "reb": 5.69, "ast": 1.56, "stl": 0.56, "blk": 0.58, "turnover": 0.66, "pf": 1.9, "pts": 12.04, "fg_pct": 0.456, "fg3_pct": 0.409, "ft_pct": 0.898}, {"games_played": 79, "player_id": 379, "season": 2017, "min": "21:09", "fgm": 3.23, "fga": 5.44, "fg3m": 0.35, "fg3a": 1.06, "ftm": 1.68, "fta": 2.34, "oreb": 1.71, "dreb": 3.91, "reb": 5.62, "ast": 1.15, "stl": 0.85, "blk": 0.41, "turnover": 0.75, "pf": 2.35, "pts": 8.49, "fg_pct": 0.593, "fg3_pct": 0.333, "ft_pct": 0.719}, {"games_played": 69, "player_id": 421, "season": 2017, "min": "29:41", "fgm": 5.86, "fga": 14.84, "fg3m": 1.54, "fg3a": 4.91, "ftm": 1.94, "fta": 2.8, "oreb": 0.72, "dreb": 3.04, "reb": 3.77, "ast": 5.19, "stl": 1.03, "blk": 0.26, "turnover": 2.81, "pf": 2.2, "pts": 15.19, "fg_pct": 0.395, "fg3_pct": 0.313, "ft_pct": 0.694}, {"games_played": 2, "player_id": 1782, "season": 2017, "min": "2:52", "fgm": 0.0, "fga": 0.5, "fg3m": 0.0, "fg3a": 0.5, "ftm": 0.0, "fta": 0.0, "oreb": 0.0, "dreb": 0.0, "reb": 0.0, "ast": 0.0, "stl": 0.0, "blk": 0.0, "turnover": 0.0, "pf": 1.0, "pts": 0.0, "fg_pct": 0.0, "fg3_pct": 0.0, "ft_pct": 0}, {"games_played": 10, "player_id": 2043, "season": 2017, "min": "3:55", "fgm": 0.6, "fga": 1.6, "fg3m": 0.2, "fg3a": 1.0, "ftm": 0.1, "fta": 0.2, "oreb": 0.1, "dreb": 0.9, "reb": 1.0, "ast": 0.0, "stl": 0.0, "blk": 0.3, "turnover": 0.2, "pf": 0.3, "pts": 1.5, "fg_pct": 0.375, "fg3_pct": 0.2, "ft_pct": 0.5}, {"games_played": 1, "player_id": 2073, "season": 2017, "min": "8:23", "fgm": 0.0, "fga": 1.0, "fg3m": 0.0, "fg3a": 0.0, "ftm": 1.0, "fta": 2.0, "oreb": 0.0, "dreb": 0.0, "reb": 0.0, "ast": 1.0, "stl": 0.0, "blk": 0.0, "turnover": 1.0, "pf": 0.0, "pts": 1.0, "fg_pct": 0.0, "fg3_pct": 0, "ft_pct": 0.5}, {"games_played": 9, "player_id": 2132, "season": 2017, "min": "25:55", "fgm": 2.11, "fga": 7.67, "fg3m": 1.0, "fg3a": 4.78, "ftm": 1.44, "fta": 1.89, "oreb": 0.44, "dreb": 2.22, "reb": 2.67, "ast": 1.22, "stl": 1.0, "blk": 0.22, "turnover": 0.33, "pf": 3.0, "pts": 6.67, "fg_pct": 0.275, "fg3_pct": 0.209, "ft_pct": 0.765}, {"games_played": 16, "player_id": 2193, "season": 2017, "min": "11:20", "fgm": 1.63, "fga": 4.25, "fg3m": 0.63, "fg3a": 1.63, "ftm": 0.75, "fta": 1.19, "oreb": 0.81, "dreb": 1.56, "reb": 2.38, "ast": 0.25, "stl": 0.31, "blk": 0.06, "turnover": 0.44, "pf": 1.38, "pts": 4.63, "fg_pct": 0.382, "fg3_pct": 0.385, "ft_pct": 0.632}, {"games_played": 7, "player_id": 2201, "season": 2017, "min": "9:05", "fgm": 0.86, "fga": 2.57, "fg3m": 0.86, "fg3a": 2.14, "ftm": 0.29, "fta": 0.29, "oreb": 0.14, "dreb": 0.86, "reb": 1.0, "ast": 0.43, "stl": 0.29, "blk": 0.0, "turnover": 0.29, "pf": 1.14, "pts": 2.86, "fg_pct": 0.333, "fg3_pct": 0.4, "ft_pct": 1.0}, {"games_played": 17, "player_id": 2211, "season": 2017, "min": "7:12", "fgm": 0.47, "fga": 1.24, "fg3m": 0.18, "fg3a": 0.24, "ftm": 0.24, "fta": 0.35, "oreb": 0.18, "dreb": 0.65, "reb": 0.82, "ast": 0.12, "stl": 0.41, "blk": 0.29, "turnover": 0.41, "pf": 1.35, "pts": 1.35, "fg_pct": 0.381, "fg3_pct": 0.75, "ft_pct": 0.667}, {"games_played": 32, "player_id": 2218, "season": 2017, "min": "14:59", "fgm": 1.19, "fga": 3.09, "fg3m": 0.13, "fg3a": 0.53, "ftm": 0.66, "fta": 1.25, "oreb": 1.0, "dreb": 2.34, "reb": 3.34, "ast": 1.75, "stl": 0.53, "blk": 0.28, "turnover": 0.75, "pf": 1.38, "pts": 3.16, "fg_pct": 0.384, "fg3_pct": 0.235, "ft_pct": 0.525}, {"games_played": 3, "player_id": 2232, "season": 2017, "min": "8:57", "fgm": 2.33, "fga": 4.0, "fg3m": 0.0, "fg3a": 0.0, "ftm": 1.0, "fta": 1.67, "oreb": 1.33, "dreb": 1.67, "reb": 3.0, "ast": 0.0, "stl": 0.0, "blk": 0.0, "turnover": 0.33, "pf": 0.67, "pts": 5.67, "fg_pct": 0.583, "fg3_pct": 0, "ft_pct": 0.6}]}