{"data":[{"ast":6.77,"blk":0.2,"dreb":3.53,"fg3_pct":0.326,"fg3a":6.47,"fg3m":2.11,"fg_pct":0.467,"fga":19.61,"fgm":9.16,"ft_pct":0.866,"fta":7.09,"ftm":6.14,"games_played":64,"seconds":2102.0,"oreb":0.61,"pf":3.13,"player_id":57,"pts":26.56,"reb":4.14,"season":2018,"stl":0.88,"turnover":4.13},{"ast":1.49,"blk":0.67,"dreb":3.33,"fg3_pct":0.428,"fg3a":4.19,"fg3m":1.79,"fg_pct":0.486,"fga":14.21,"fgm":6.91,"ft_pct":0.815,"fta":2.88,"ftm":2.35,"games_played":43,"seconds":1897.0,"oreb":0.72,"pf":2.77,"player_id":469,"pts":17.95,"reb":4.05,"season":2018,"stl":1.19,"turnover":1.21},{"ast":1.76,"blk":0.94,"dreb":7.13,"fg3_pct":0.0,"fg3a":0.06,"fg3m":0.0,"fg_pct":0.585,"fga":12.25,"fgm":7.17,"ft_pct":0.746,"fta":2.66,"ftm":1.99,"games_played":71,"seconds":1844.0,"oreb":3.14,"pf":2.94,"player_id":22,"pts":16.32,"reb":10.27,"season":2018,"stl":0.86,"turnover":1.77},{"ast":2.11,"blk":0.46,"dreb":2.55,"fg3_pct":0.335,"fg3a":3.82,"fg3m":1.28,"fg_pct":0.43,"fga":6.87,"fgm":2.95,"ft_pct":0.805,"fta":1.44,"ftm":1.16,"games_played":82,"seconds":1768.0,"oreb":0.68,"pf":2.45,"player_id":61,"pts":8.34,"reb":3.23,"season":2018,"stl":1.56,"turnover":0.85},{"ast":1.22,"blk":0.86,"dreb":3.68,"fg3_pct":0.32,"fg3a":4.9,"fg3m":1.57,"fg_pct":0.445,"fga":12.2,"fgm":5.43,"ft_pct":0.775,"fta":3.54,"ftm":2.74,"games_played":69,"seconds":1682.0,"oreb":1.03,"pf":2.62,"player_id":360,"pts":15.17,"reb":4.71,"season":2018,"stl":1.22,"turnover":1.49},{"ast":2.32,"blk":0.71,"dreb":3.56,"fg3_pct":0.324,"fg3a":2.85,"fg3m":0.92,"fg_pct":0.413,"fga":10.65,"fgm":4.39,"ft_pct":0.671,"fta":2.7,"ftm":1.81,"games_played":79,"seconds":1509.0,"oreb":0.84,"pf":2.65,"player_id":234,"pts":11.52,"reb":4.39,"season":2018,"stl":0.94,"turnover":2.19},{"ast":2.71,"blk":0.06,"dreb":1.68,"fg3_pct":0.354,"fg3a":3.1,"fg3m":1.1,"fg_pct":0.39,"fga":5.29,"fgm":2.06,"ft_pct":0.792,"fta":0.77,"ftm":0.61,"games_played":31,"seconds":1215.0,"oreb":0.19,"pf":1.68,"player_id":82,"pts":5.84,"reb":1.87,"season":2018,"stl":0.45,"turnover":1.13},{"ast":1.19,"blk":0.49,"dreb":3.17,"fg3_pct":0.218,"fg3a":2.15,"fg3m":0.47,"fg_pct":0.447,"fga":4.19,"fgm":1.87,"ft_pct":0.593,"fta":1.15,"ftm":0.68,"games_played":47,"seconds":1054.0,"oreb":0.72,"pf":1.91,"player_id":43,"pts":4.89,"reb":3.89,"season":2018,"stl":0.38,"turnover":0.79},{"ast":2.84,"blk":0.41,"dreb":1.95,"fg3_pct":0.305,"fg3a":1.7,"fg3m":0.52,"fg_pct":0.391,"fga":4.57,"fgm":1.79,"ft_pct":0.75,"fta":0.5,"ftm":0.38,"games_played":56,"seconds":1054.0,"oreb":0.45,"pf":2.02,"player_id":313,"pts":4.46,"reb":2.39,"season":2018,"stl":1.21,"turnover":1.34},{"ast":0.86,"blk":1.13,"dreb":3.09,"fg3_pct":0.0,"fg3a":0.0,"fg3m":0.0,"fg_pct":0.608,"fga":5.21,"fgm":3.17,"ft_pct":0.731,"fta":2.5,"ftm":1.83,"games_played":70,"seconds":1014.0,"oreb":1.64,"pf":2.77,"player_id":217,"pts":8.17,"reb":4.73,"season":2018,"stl":0.6,"turnover":0.74},{"ast":3.18,"blk":0.17,"dreb":1.07,"fg3_pct":0.332,"fg3a":2.81,"fg3m":0.93,"fg_pct":0.397,"fga":6.08,"fgm":2.42,"ft_pct":0.845,"fta":1.53,"ftm":1.29,"games_played":72,"seconds":1009.0,"oreb":0.11,"pf":1.04,"player_id":111,"pts":7.06,"reb":1.18,"season":2018,"stl":0.46,"turnover":1.38},{"ast":2.08,"blk":0.11,"dreb":1.41,"fg3_pct":0.295,"fg3a":2.16,"fg3m":0.64,"fg_pct":0.393,"fga":4.75,"fgm":1.87,"ft_pct":0.787,"fta":0.77,"ftm":0.61,"games_played":61,"seconds":942.0,"oreb":0.2,"pf":1.79,"player_id":355,"pts":4.98,"reb":1.61,"season":2018,"stl":0.52,"turnover":1.13}]}
